<?xml version="1.0" encoding="utf-8" ?>
<dwsync>
<file name="index.html" server="ftp.turkcadcam.net" local="131514796264681869" remote="131514593400000000" />
<file name="index2.html" server="ftp.turkcadcam.net" local="131514796265555979" remote="131514593400000000" />
<file name="index3.html" server="ftp.turkcadcam.net" local="131514796266393324" remote="131514593400000000" />
<file name="01.gif" server="server251.web-hosting.com/public_html/" local="128389761272500000" remote="131535392400000000" />
<file name="02.png" server="server251.web-hosting.com/public_html/" local="128389762473125000" remote="131535392400000000" />
<file name="03.png" server="server251.web-hosting.com/public_html/" local="128389733109218750" remote="131535392400000000" />
<file name="04.png" server="server251.web-hosting.com/public_html/" local="128389733316093750" remote="131535392400000000" />
<file name="05.png" server="server251.web-hosting.com/public_html/" local="128389733535468750" remote="131535392400000000" />
<file name="06.png" server="server251.web-hosting.com/public_html/" local="128389733716250000" remote="131535392400000000" />
<file name="07.png" server="server251.web-hosting.com/public_html/" local="128389734425156250" remote="131535392400000000" />
<file name="08.png" server="server251.web-hosting.com/public_html/" local="128389734330156250" remote="131535392400000000" />
<file name="09.png" server="server251.web-hosting.com/public_html/" local="128389734227187500" remote="131535392400000000" />
<file name="10.jpg" server="server251.web-hosting.com/public_html/" local="128389734645937500" remote="131535392400000000" />
<file name="11.jpg" server="server251.web-hosting.com/public_html/" local="128389735303750000" remote="131535392400000000" />
<file name="12.jpg" server="server251.web-hosting.com/public_html/" local="128389735489375000" remote="131535392400000000" />
<file name="13-t.jpg" server="server251.web-hosting.com/public_html/" local="128389766446562500" remote="131535393000000000" />
<file name="13.jpg" server="server251.web-hosting.com/public_html/" local="128389735597812500" remote="131535393000000000" />
<file name="14.jpg" server="server251.web-hosting.com/public_html/" local="128389735715312500" remote="131535393000000000" />
<file name="15.jpg" server="server251.web-hosting.com/public_html/" local="128389735809062500" remote="131535393000000000" />
<file name="arge-logo.jpg" server="server251.web-hosting.com/public_html/" local="128389732231718750" remote="131535393000000000" />
<file name="index.html" server="server251.web-hosting.com/public_html/" local="131529627609259514" remote="131535393000000000" />
<file name="index2.html" server="server251.web-hosting.com/public_html/" local="131529627610399879" remote="131535393000000000" />
<file name="index3.html" server="server251.web-hosting.com/public_html/" local="131529627611521205" remote="131535393000000000" />
</dwsync>