<?xml version="1.0" encoding="utf-8" ?>
<dwsync>
<file name="kizilca-01.html" server="ftp.turkcadcam.net" local="131514135072167513" remote="131513921400000000" />
<file name="petrotec-01.html" server="ftp.turkcadcam.net" local="131514135084381759" remote="131513921400000000" />
<file name="nikken-09.html" server="ftp.turkcadcam.net" local="131514135079542732" remote="131513921400000000" />
<file name="nikken-05.html" server="ftp.turkcadcam.net" local="131514135078762150" remote="131513921400000000" />
<file name="nikken-06.html" server="ftp.turkcadcam.net" local="131514135078962330" remote="131513921400000000" />
<file name="nikken-07.html" server="ftp.turkcadcam.net" local="131514135079152443" remote="131513921400000000" />
<file name="nikken-08.html" server="ftp.turkcadcam.net" local="131514135079342586" remote="131513921400000000" />
<file name="revizyon-makina-04.html" server="ftp.turkcadcam.net" local="131514135091659790" remote="131513922000000000" />
<file name="mtn-01.html" server="ftp.turkcadcam.net" local="131514135077791488" remote="131513921400000000" />
<file name="makkalip-03.html" server="ftp.turkcadcam.net" local="131514135073358347" remote="131513921400000000" />
<file name="ninamedikal-01.html" server="ftp.turkcadcam.net" local="131514135080309035" remote="131513921400000000" />
<file name="inores-01.html" server="ftp.turkcadcam.net" local="131514135065207797" remote="131513920800000000" />
<file name="delcam-02.html" server="ftp.turkcadcam.net" local="131514135054763465" remote="131513920800000000" />
<file name="3b-dizayn-02.html" server="ftp.turkcadcam.net" local="131514135033315064" remote="131513920200000000" />
<file name="3dcadcam-02-old.html" server="ftp.turkcadcam.net" local="131514135033505199" remote="131513920200000000" />
<file name="3dcadcam-02.html" server="ftp.turkcadcam.net" local="131514135033695333" remote="131513920200000000" />
<file name="3ds-01.html" server="ftp.turkcadcam.net" local="131514135033895539" remote="131513920200000000" />
<file name="4cmedikal-01.html" server="ftp.turkcadcam.net" local="131514135034085609" remote="131513920200000000" />
<file name="4cmedikal-02.html" server="ftp.turkcadcam.net" local="131514135034275744" remote="131513920200000000" />
<file name="4cmedikal-03.html" server="ftp.turkcadcam.net" local="131514135034465878" remote="131513920200000000" />
<file name="4cmedikal-04.html" server="ftp.turkcadcam.net" local="131514135034656013" remote="131513920200000000" />
<file name="4cmedikal-05.html" server="ftp.turkcadcam.net" local="131514135034836140" remote="131513920200000000" />
<file name="4cmedikal-06.html" server="ftp.turkcadcam.net" local="131514135035026275" remote="131513920200000000" />
<file name="4cmedikal-07.html" server="ftp.turkcadcam.net" local="131514135035216410" remote="131513920200000000" />
<file name="4cmedikal-08-iptal.html" server="ftp.turkcadcam.net" local="131514135035406548" remote="131513920200000000" />
<file name="4cmedikal-08.html" server="ftp.turkcadcam.net" local="131514135035586672" remote="131513920200000000" />
<file name="aat-01.html" server="ftp.turkcadcam.net" local="131514135036147068" remote="131513920200000000" />
<file name="aba-otomotiv-01.html" server="ftp.turkcadcam.net" local="131514135036327196" remote="131513920200000000" />
<file name="abcadcam-01.html" server="ftp.turkcadcam.net" local="131514135036517330" remote="131513920200000000" />
<file name="abcadcam-02.html" server="ftp.turkcadcam.net" local="131514135036707465" remote="131513920200000000" />
<file name="abigem-kocaeli-01.html" server="ftp.turkcadcam.net" local="131514135036897599" remote="131513920200000000" />
<file name="ACMT-Makine-01.html" server="ftp.turkcadcam.net" local="131514135037087734" remote="131513920200000000" />
<file name="adam-01.html" server="ftp.turkcadcam.net" local="131514135037277868" remote="131513920200000000" />
<file name="adim-01.html" server="ftp.turkcadcam.net" local="131514135037457996" remote="131513920200000000" />
<file name="akana-01.html" server="ftp.turkcadcam.net" local="131514135037638123" remote="131513920200000000" />
<file name="akmetal-01.html" server="ftp.turkcadcam.net" local="131514135037828258" remote="131513920200000000" />
<file name="albakalip-03.html" server="ftp.turkcadcam.net" local="131514135038419972" remote="131513920200000000" />
<file name="aldes-01.html" server="ftp.turkcadcam.net" local="131514135038610115" remote="131513920200000000" />
<file name="alfa-01.html" server="ftp.turkcadcam.net" local="131514135038810261" remote="131513920200000000" />
<file name="alpar-01.html" server="ftp.turkcadcam.net" local="131514135038990384" remote="131513920200000000" />
<file name="alpar-02.html" server="ftp.turkcadcam.net" local="131514135039180527" remote="131513920200000000" />
<file name="altanhidrolik-01.html" server="ftp.turkcadcam.net" local="131514135039370649" remote="131513920200000000" />
<file name="altar-08.html" server="ftp.turkcadcam.net" local="131514135039570799" remote="131513920200000000" />
<file name="altar-09.html" server="ftp.turkcadcam.net" local="131514135039760925" remote="131513920200000000" />
<file name="altin-kristal-01.html" server="ftp.turkcadcam.net" local="131514135039941052" remote="131513920200000000" />
<file name="altunorak-01.html" server="ftp.turkcadcam.net" local="131514135040141258" remote="131513920200000000" />
<file name="altunorak-02.html" server="ftp.turkcadcam.net" local="131514135040321321" remote="131513920200000000" />
<file name="altunorak-03.html" server="ftp.turkcadcam.net" local="131514135040511456" remote="131513920200000000" />
<file name="anarotomotiv-01.html" server="ftp.turkcadcam.net" local="131514135040881718" remote="131513920200000000" />
<file name="ar-is-01.html" server="ftp.turkcadcam.net" local="131514135041071853" remote="131513920200000000" />
<file name="ar-is-02.html" server="ftp.turkcadcam.net" local="131514135041271998" remote="131513920200000000" />
<file name="ar-is-03.html" server="ftp.turkcadcam.net" local="131514135041482151" remote="131513920200000000" />
<file name="araslube-01.html" server="ftp.turkcadcam.net" local="131514135041682242" remote="131513920200000000" />
<file name="argemuhendislik-06.html" server="ftp.turkcadcam.net" local="131514135041882430" remote="131513920200000000" />
<file name="aritas-01.html" server="ftp.turkcadcam.net" local="131514135042081978" remote="131513920200000000" />
<file name="armada-01.html" server="ftp.turkcadcam.net" local="131514135042482257" remote="131513920200000000" />
<file name="armada-02.html" server="ftp.turkcadcam.net" local="131514135042692410" remote="131513920200000000" />
<file name="armadental-01.html" server="ftp.turkcadcam.net" local="131514135043082686" remote="131513920200000000" />
<file name="arpas-02.html" server="ftp.turkcadcam.net" local="131514135043282828" remote="131513920200000000" />
<file name="array-01.html" server="ftp.turkcadcam.net" local="131514135043482973" remote="131513920200000000" />
<file name="artikalip-01.html" server="ftp.turkcadcam.net" local="131514135043683111" remote="131513920200000000" />
<file name="atadizayn-01.html" server="ftp.turkcadcam.net" local="131514135043883248" remote="131513920200000000" />
<file name="atalan-makine-04.html" server="ftp.turkcadcam.net" local="131514135044083390" remote="131513920200000000" />
<file name="avrotas-03.html" server="ftp.turkcadcam.net" local="131514135044283536" remote="131513920200000000" />
<file name="avrotas-04.html" server="ftp.turkcadcam.net" local="131514135044473666" remote="131513920200000000" />
<file name="baykarmakina-02.html" server="ftp.turkcadcam.net" local="131514135044883781" remote="131513920200000000" />
<file name="bdtyazilim-01.html" server="ftp.turkcadcam.net" local="131514135045084111" remote="131513920200000000" />
<file name="bdtyazilim-02.html" server="ftp.turkcadcam.net" local="131514135045284235" remote="131513920200000000" />
<file name="bedir-01.html" server="ftp.turkcadcam.net" local="131514135045494311" remote="131513920200000000" />
<file name="bedir-02.html" server="ftp.turkcadcam.net" local="131514135045704533" remote="131513920200000000" />
<file name="bemis-01.html" server="ftp.turkcadcam.net" local="131514135045914682" remote="131513920200000000" />
<file name="bias-02.html" server="ftp.turkcadcam.net" local="131514135046114832" remote="131513920800000000" />
<file name="bicakcilar-01.html" server="ftp.turkcadcam.net" local="131514135046314969" remote="131513920800000000" />
<file name="bimex-04.html" server="ftp.turkcadcam.net" local="131514135046523980" remote="131513920800000000" />
<file name="bogazici-yazilim-03.html" server="ftp.turkcadcam.net" local="131514135046724323" remote="131513920800000000" />
<file name="bogazici-yazilim-04.html" server="ftp.turkcadcam.net" local="131514135046924464" remote="131513920800000000" />
<file name="bogazici-yazilim-05.html" server="ftp.turkcadcam.net" local="131514135047134566" remote="131513920800000000" />
<file name="boyut-cnc-01.html" server="ftp.turkcadcam.net" local="131514135047334759" remote="131513920800000000" />
<file name="boyut-cnc-02.html" server="ftp.turkcadcam.net" local="131514135047534901" remote="131513920800000000" />
<file name="boyut-cnc-03.html" server="ftp.turkcadcam.net" local="131514135047745002" remote="131513920800000000" />
<file name="boyut-cnc-04.html" server="ftp.turkcadcam.net" local="131514135047945187" remote="131513920800000000" />
<file name="boyut-cnc-05.html" server="ftp.turkcadcam.net" local="131514135048145328" remote="131513920800000000" />
<file name="bozkurtmodel-01.html" server="ftp.turkcadcam.net" local="131514135048345432" remote="131513920800000000" />
<file name="BSA-bilg-01.html" server="ftp.turkcadcam.net" local="131514135048745749" remote="131513920800000000" />
<file name="BSA-bilg-02.html" server="ftp.turkcadcam.net" local="131514135048935884" remote="131513920800000000" />
<file name="bures-01.html" server="ftp.turkcadcam.net" local="131514135049135876" remote="131513920800000000" />
<file name="cadem-09.html" server="ftp.turkcadcam.net" local="131514135049716440" remote="131513920800000000" />
<file name="cadem-10.html" server="ftp.turkcadcam.net" local="131514135049906575" remote="131513920800000000" />
<file name="cadem-11.html" server="ftp.turkcadcam.net" local="131514135050220417" remote="131513920800000000" />
<file name="cadem-12.html" server="ftp.turkcadcam.net" local="131514135050410547" remote="131513920800000000" />
<file name="cadem-13.html" server="ftp.turkcadcam.net" local="131514135050600677" remote="131513920800000000" />
<file name="cadem-14.html" server="ftp.turkcadcam.net" local="131514135050790816" remote="131513920800000000" />
<file name="cadem-15.html" server="ftp.turkcadcam.net" local="131514135050990953" remote="131513920800000000" />
<file name="cadem-16.html" server="ftp.turkcadcam.net" local="131514135051230965" remote="131513920800000000" />
<file name="cadem-17.html" server="ftp.turkcadcam.net" local="131514135051451121" remote="131513920800000000" />
<file name="cagcadcam-03.html" server="ftp.turkcadcam.net" local="131514135051661355" remote="131513920800000000" />
<file name="cagcadcam-04.html" server="ftp.turkcadcam.net" local="131514135051861527" remote="131513920800000000" />
<file name="cagri-end-08.html" server="ftp.turkcadcam.net" local="131514135052061707" remote="131513920800000000" />
<file name="cagri-end-09.html" server="ftp.turkcadcam.net" local="131514135052251850" remote="131513920800000000" />
<file name="cozumkalip-01.html" server="ftp.turkcadcam.net" local="131514135052862295" remote="131513920800000000" />
<file name="cozumkalip-02.html" server="ftp.turkcadcam.net" local="131514135053062445" remote="131513920800000000" />
<file name="cozumkalip-03.html" server="ftp.turkcadcam.net" local="131514135053292510" remote="131513920800000000" />
<file name="dahirinsaat-01.html" server="ftp.turkcadcam.net" local="131514135053512708" remote="131513920800000000" />
<file name="dalelektronik-01.html" server="ftp.turkcadcam.net" local="131514135053722895" remote="131513920800000000" />
<file name="dekortools-01.html" server="ftp.turkcadcam.net" local="131514135053943000" remote="131513920800000000" />
<file name="dekortools-02.html" server="ftp.turkcadcam.net" local="131514135054143141" remote="131513920800000000" />
<file name="delcam-01.html" server="ftp.turkcadcam.net" local="131514135054563375" remote="131513920800000000" />
<file name="dema3000-01.html" server="ftp.turkcadcam.net" local="131514135055173760" remote="131513920800000000" />
<file name="desa-01.html" server="ftp.turkcadcam.net" local="131514135055383896" remote="131513920800000000" />
<file name="dostel-01.html" server="ftp.turkcadcam.net" local="131514135055584037" remote="131513920800000000" />
<file name="dreambox-01.html" server="ftp.turkcadcam.net" local="131514135055784307" remote="131513920800000000" />
<file name="dunyakalip-01.html" server="ftp.turkcadcam.net" local="131514135055984445" remote="131513920800000000" />
<file name="efeendustri-01.html" server="ftp.turkcadcam.net" local="131514135057235330" remote="131513920800000000" />
<file name="ekerplastik-01.html" server="ftp.turkcadcam.net" local="131514135057445483" remote="131513920800000000" />
<file name="ekinler-03-old.html" server="ftp.turkcadcam.net" local="131514135057655632" remote="131513920800000000" />
<file name="ekinler-03.html" server="ftp.turkcadcam.net" local="131514135057875834" remote="131513920800000000" />
<file name="eksen-02.html" server="ftp.turkcadcam.net" local="131514135058075929" remote="131513920800000000" />
<file name="eksenkalip-01.html" server="ftp.turkcadcam.net" local="131514135058486215" remote="131513920800000000" />
<file name="elfjet-01.html" server="ftp.turkcadcam.net" local="131514135058686361" remote="131513920800000000" />
<file name="elfjet-02.html" server="ftp.turkcadcam.net" local="131514135058893388" remote="131513920800000000" />
<file name="elmaplastik-01.html" server="ftp.turkcadcam.net" local="131514135059303670" remote="131513920800000000" />
<file name="ender-01.html" server="ftp.turkcadcam.net" local="131514135059513874" remote="131513920800000000" />
<file name="enformak-01.html" server="ftp.turkcadcam.net" local="131514135059723976" remote="131513920800000000" />
<file name="enformak-02.html" server="ftp.turkcadcam.net" local="131514135059924109" remote="131513920800000000" />
<file name="ermakina-01.html" server="ftp.turkcadcam.net" local="131514135060134262" remote="131513920800000000" />
<file name="evreko-01.html" server="ftp.turkcadcam.net" local="131514135060334399" remote="131513920800000000" />
<file name="fatih-univ-01.html" server="ftp.turkcadcam.net" local="131514135060734734" remote="131513920800000000" />
<file name="fetih-plastik-07.html" server="ftp.turkcadcam.net" local="131514135060924860" remote="131513920800000000" />
<file name="fetih-plastik-08.html" server="ftp.turkcadcam.net" local="131514135061134974" remote="131513920800000000" />
<file name="fibrobeton-01.html" server="ftp.turkcadcam.net" local="131514135061345123" remote="131513920800000000" />
<file name="ge-mtc-03.html" server="ftp.turkcadcam.net" local="131514135061555267" remote="131513920800000000" />
<file name="ge-mtc-04.html" server="ftp.turkcadcam.net" local="131514135061765574" remote="131513920800000000" />
<file name="girginler-01.html" server="ftp.turkcadcam.net" local="131514135062165699" remote="131513920800000000" />
<file name="girginler-02.html" server="ftp.turkcadcam.net" local="131514135062365888" remote="131513920800000000" />
<file name="glassco-01.html" server="ftp.turkcadcam.net" local="131514135062565983" remote="131513920800000000" />
<file name="glassco-02.html" server="ftp.turkcadcam.net" local="131514135062766120" remote="131513920800000000" />
<file name="hakanunlu-01.html" server="ftp.turkcadcam.net" local="131514135062966304" remote="131513920800000000" />
<file name="hexagon-01.html" server="ftp.turkcadcam.net" local="131514135063356589" remote="131513920800000000" />
<file name="hidroser-01.html" server="ftp.turkcadcam.net" local="131514135063556821" remote="131513920800000000" />
<file name="hidrotam-02.html" server="ftp.turkcadcam.net" local="131514135063756864" remote="131513920800000000" />
<file name="hidrotam-03.html" server="ftp.turkcadcam.net" local="131514135063957014" remote="131513920800000000" />
<file name="hofmann-turk-01.html" server="ftp.turkcadcam.net" local="131514135064377329" remote="131513920800000000" />
<file name="hofmann-turk-02.html" server="ftp.turkcadcam.net" local="131514135064597318" remote="131513920800000000" />
<file name="imren-plastik-01.html" server="ftp.turkcadcam.net" local="131514135064807625" remote="131513920800000000" />
<file name="imren-plastik-02.html" server="ftp.turkcadcam.net" local="131514135065007698" remote="131513920800000000" />
<file name="intexis-01.html" server="ftp.turkcadcam.net" local="131514135065402682" remote="131513920800000000" />
<file name="islem-01.html" server="ftp.turkcadcam.net" local="131514135065602820" remote="131513920800000000" />
<file name="islem-02.html" server="ftp.turkcadcam.net" local="131514135065812968" remote="131513920800000000" />
<file name="islem-03.html" server="ftp.turkcadcam.net" local="131514135066003150" remote="131513920800000000" />
<file name="ivesta-01.html" server="ftp.turkcadcam.net" local="131514135066203253" remote="131513920800000000" />
<file name="kaanmakina-02.html" server="ftp.turkcadcam.net" local="131514135066593568" remote="131513920800000000" />
<file name="kaban-01.html" server="ftp.turkcadcam.net" local="131514135066783694" remote="131513920800000000" />
<file name="kahraman-kalip-03.html" server="ftp.turkcadcam.net" local="131514135066973833" remote="131513921400000000" />
<file name="kahraman-kalip-04.html" server="ftp.turkcadcam.net" local="131514135067163967" remote="131513921400000000" />
<file name="kahraman-kalip-05.html" server="ftp.turkcadcam.net" local="131514135067354098" remote="131513921400000000" />
<file name="kahraman-kalip-06.html" server="ftp.turkcadcam.net" local="131514135067544228" remote="131513921400000000" />
<file name="kale-havacilik-01.html" server="ftp.turkcadcam.net" local="131514135067734367" remote="131513921400000000" />
<file name="kale-havacilik-02.html" server="ftp.turkcadcam.net" local="131514135067924501" remote="131513921400000000" />
<file name="kale-havacilik-03.html" server="ftp.turkcadcam.net" local="131514135068114636" remote="131513921400000000" />
<file name="kale-havacilik-04.html" server="ftp.turkcadcam.net" local="131514135068304766" remote="131513921400000000" />
<file name="kale-havacilik-05.html" server="ftp.turkcadcam.net" local="131514135068494905" remote="131513921400000000" />
<file name="kale-havacilik-06.html" server="ftp.turkcadcam.net" local="131514135068685044" remote="131513921400000000" />
<file name="kale-havacilik-07.html" server="ftp.turkcadcam.net" local="131514135068885185" remote="131513921400000000" />
<file name="kale-havacilik-08.html" server="ftp.turkcadcam.net" local="131514135069075320" remote="131513921400000000" />
<file name="kale-havacilik-09.html" server="ftp.turkcadcam.net" local="131514135069275457" remote="131513921400000000" />
<file name="kale-havacilik-10.html" server="ftp.turkcadcam.net" local="131514135069465596" remote="131513921400000000" />
<file name="kale-havacilik-11.html" server="ftp.turkcadcam.net" local="131514135069665734" remote="131513921400000000" />
<file name="kale-havacilik-12.html" server="ftp.turkcadcam.net" local="131514135069855872" remote="131513921400000000" />
<file name="kale-havacilik-13.html" server="ftp.turkcadcam.net" local="131514135070046003" remote="131513921400000000" />
<file name="kalekalip-havacilik-07.html" server="ftp.turkcadcam.net" local="131514135070616406" remote="131513921400000000" />
<file name="kalekalip-havacilik-08.html" server="ftp.turkcadcam.net" local="131514135070816552" remote="131513921400000000" />
<file name="kalip-destek-01.html" server="ftp.turkcadcam.net" local="131514135071006687" remote="131513921400000000" />
<file name="kalip-destek-02.html" server="ftp.turkcadcam.net" local="131514135071196817" remote="131513921400000000" />
<file name="kemsan-01.html" server="ftp.turkcadcam.net" local="131514135071777236" remote="131513921400000000" />
<file name="kismetcnc-01.html" server="ftp.turkcadcam.net" local="131514135071967362" remote="131513921400000000" />
<file name="komet-01.html" server="ftp.turkcadcam.net" local="131514135072367658" remote="131513921400000000" />
<file name="magmatasarim-01.html" server="ftp.turkcadcam.net" local="131514135072777919" remote="131513921400000000" />
<file name="makkalip-01.html" server="ftp.turkcadcam.net" local="131514135072968071" remote="131513921400000000" />
<file name="makyay-01.html" server="ftp.turkcadcam.net" local="131514135074118885" remote="131513921400000000" />
<file name="manus-01.html" server="ftp.turkcadcam.net" local="131514135074319027" remote="131513921400000000" />
<file name="markalip-01.html" server="ftp.turkcadcam.net" local="131514135074509165" remote="131513921400000000" />
<file name="markalip-02.html" server="ftp.turkcadcam.net" local="131514135074709260" remote="131513921400000000" />
<file name="markalip-03.html" server="ftp.turkcadcam.net" local="131514135074899442" remote="131513921400000000" />
<file name="maysat-02.html" server="ftp.turkcadcam.net" local="131514135075659976" remote="131513921400000000" />
<file name="mekano-01.html" server="ftp.turkcadcam.net" local="131514135075860169" remote="131513921400000000" />
<file name="mfk-01.html" server="ftp.turkcadcam.net" local="131514135076240386" remote="131513921400000000" />
<file name="mfs-01.html" server="ftp.turkcadcam.net" local="131514135076430521" remote="131513921400000000" />
<file name="mfs-02.html" server="ftp.turkcadcam.net" local="131514135076630663" remote="131513921400000000" />
<file name="mfs-03.html" server="ftp.turkcadcam.net" local="131514135076820797" remote="131513921400000000" />
<file name="milimetrik-01.html" server="ftp.turkcadcam.net" local="131514135077020943" remote="131513921400000000" />
<file name="modus-01.html" server="ftp.turkcadcam.net" local="131514135077211078" remote="131513921400000000" />
<file name="modus-02.html" server="ftp.turkcadcam.net" local="131514135077411048" remote="131513921400000000" />
<file name="mt-01.html" server="ftp.turkcadcam.net" local="131514135077601358" remote="131513921400000000" />
<file name="mubitek-01.html" server="ftp.turkcadcam.net" local="131514135077981623" remote="131513921400000000" />
<file name="murat-01.html" server="ftp.turkcadcam.net" local="131514135078161746" remote="131513921400000000" />
<file name="neksus-01.html" server="ftp.turkcadcam.net" local="131514135078361888" remote="131513921400000000" />
<file name="nesne-emt-01.html" server="ftp.turkcadcam.net" local="131514135078562072" remote="131513921400000000" />
<file name="nkg-01.html" server="ftp.turkcadcam.net" local="131514135080499174" remote="131513921400000000" />
<file name="ntg-plastik-01.html" server="ftp.turkcadcam.net" local="131514135080679301" remote="131513921400000000" />
<file name="ntg-plastik-02.html" server="ftp.turkcadcam.net" local="131514135080879439" remote="131513921400000000" />
<file name="ntg-plastik-03.html" server="ftp.turkcadcam.net" local="131514135081069577" remote="131513921400000000" />
<file name="numarine-01.html" server="ftp.turkcadcam.net" local="131514135081449851" remote="131513921400000000" />
<file name="orsaproje-01.html" server="ftp.turkcadcam.net" local="131514135081830116" remote="131513921400000000" />
<file name="orsaproje-02.html" server="ftp.turkcadcam.net" local="131514135082020250" remote="131513921400000000" />
<file name="ostim-01.html" server="ftp.turkcadcam.net" local="131514135083020800" remote="131513921400000000" />
<file name="ozmikromak-01.html" server="ftp.turkcadcam.net" local="131514135083421075" remote="131513921400000000" />
<file name="ozugurlu-makina-02.html" server="ftp.turkcadcam.net" local="131514135083611214" remote="131513921400000000" />
<file name="pals-01.html" server="ftp.turkcadcam.net" local="131514135083801353" remote="131513921400000000" />
<file name="pals-02.html" server="ftp.turkcadcam.net" local="131514135083991483" remote="131513921400000000" />
<file name="parametrik-makina-01.html" server="ftp.turkcadcam.net" local="131514135084191624" remote="131513921400000000" />
<file name="pimeks-01.html" server="ftp.turkcadcam.net" local="131514135084581896" remote="131513921400000000" />
<file name="piramtek-01-old.html" server="ftp.turkcadcam.net" local="131514135084972177" remote="131513921400000000" />
<file name="piramtek-01.html" server="ftp.turkcadcam.net" local="131514135085172319" remote="131513921400000000" />
<file name="pirimer-01.html" server="ftp.turkcadcam.net" local="131514135085362453" remote="131513921400000000" />
<file name="plascam-01.html" server="ftp.turkcadcam.net" local="131514135085552588" remote="131513921400000000" />
<file name="plascam-02.html" server="ftp.turkcadcam.net" local="131514135085752729" remote="131513921400000000" />
<file name="plascam-03.html" server="ftp.turkcadcam.net" local="131514135085952875" remote="131513921400000000" />
<file name="plascam-04.html" server="ftp.turkcadcam.net" local="131514135086153004" remote="131513921400000000" />
<file name="plascam-05.html" server="ftp.turkcadcam.net" local="131514135086353317" remote="131513921400000000" />
<file name="plascam-06.html" server="ftp.turkcadcam.net" local="131514135086563470" remote="131513922000000000" />
<file name="plascam-07.html" server="ftp.turkcadcam.net" local="131514135086763432" remote="131513922000000000" />
<file name="plascam-08.html" server="ftp.turkcadcam.net" local="131514135086953742" remote="131513922000000000" />
<file name="plast-met-08.html" server="ftp.turkcadcam.net" local="131514135087163895" remote="131513922000000000" />
<file name="platin-kalip-01.html" server="ftp.turkcadcam.net" local="131514135087589927" remote="131513922000000000" />
<file name="platin-kalip-02.html" server="ftp.turkcadcam.net" local="131514135087820085" remote="131513922000000000" />
<file name="plus-education-01.html" server="ftp.turkcadcam.net" local="131514135088070263" remote="131513922000000000" />
<file name="plus90-01.html" server="ftp.turkcadcam.net" local="131514135088270391" remote="131513922000000000" />
<file name="pobusan-01.html" server="ftp.turkcadcam.net" local="131514135088477517" remote="131513922000000000" />
<file name="putzmeister-01.html" server="ftp.turkcadcam.net" local="131514135089458241" remote="131513922000000000" />
<file name="rasem-01.html" server="ftp.turkcadcam.net" local="131514135089648550" remote="131513922000000000" />
<file name="rayba-01.html" server="ftp.turkcadcam.net" local="131514135089848645" remote="131513922000000000" />
<file name="redoks-01.html" server="ftp.turkcadcam.net" local="131514135090048654" remote="131513922000000000" />
<file name="redoks-02.html" server="ftp.turkcadcam.net" local="131514135090258799" remote="131513922000000000" />
<file name="remicnc-01.html" server="ftp.turkcadcam.net" local="131514135090458940" remote="131513922000000000" />
<file name="remicnc-02.html" server="ftp.turkcadcam.net" local="131514135090649079" remote="131513922000000000" />
<file name="remicnc-03.html" server="ftp.turkcadcam.net" local="131514135090869231" remote="131513922000000000" />
<file name="revizyon-makina-01.html" server="ftp.turkcadcam.net" local="131514135091059365" remote="131513922000000000" />
<file name="revizyon-makina-02.html" server="ftp.turkcadcam.net" local="131514135091259507" remote="131513922000000000" />
<file name="revizyon-makina-03.html" server="ftp.turkcadcam.net" local="131514135091459653" remote="131513922000000000" />
<file name="romak-01.html" server="ftp.turkcadcam.net" local="131514135092050066" remote="131513922000000000" />
<file name="rozmas-03.html" server="ftp.turkcadcam.net" local="131514135092250212" remote="131513922000000000" />
<file name="rsa-01.html" server="ftp.turkcadcam.net" local="131514135092440342" remote="131513922000000000" />
<file name="safaksan-02.html" server="ftp.turkcadcam.net" local="131514135092660498" remote="131513922000000000" />
<file name="sahinoglu-01.html" server="ftp.turkcadcam.net" local="131514135092870647" remote="131513922000000000" />
<file name="sahinoglu-02.html" server="ftp.turkcadcam.net" local="131514135093070789" remote="131513922000000000" />
<file name="sanaltasarim-01.html" server="ftp.turkcadcam.net" local="131514135093279466" remote="131513922000000000" />
<file name="sanaltasarim-02.html" server="ftp.turkcadcam.net" local="131514135093479762" remote="131513922000000000" />
<file name="sanaltasarim-03.html" server="ftp.turkcadcam.net" local="131514135093689910" remote="131513922000000000" />
<file name="sato-plastik-02.html" server="ftp.turkcadcam.net" local="131514135094090254" remote="131513922000000000" />
<file name="sato-plastik-03.html" server="ftp.turkcadcam.net" local="131514135094450449" remote="131513922000000000" />
<file name="sato-plastik-04.html" server="ftp.turkcadcam.net" local="131514135094660593" remote="131513922000000000" />
<file name="sazcilar-01.html" server="ftp.turkcadcam.net" local="131514135095471175" remote="131513922000000000" />
<file name="sema-02.html" server="ftp.turkcadcam.net" local="131514135095701214" remote="131513922000000000" />
<file name="semmak-03.html" server="ftp.turkcadcam.net" local="131514135095931510" remote="131513922000000000" />
<file name="semmak-04.html" server="ftp.turkcadcam.net" local="131514135096171757" remote="131513922000000000" />
<file name="sistemmak-01.html" server="ftp.turkcadcam.net" local="131514135096601976" remote="131513922000000000" />
<file name="solidteknoloji-01.html" server="ftp.turkcadcam.net" local="131514135096812176" remote="131513922000000000" />
<file name="star-01.html" server="ftp.turkcadcam.net" local="131514135097012266" remote="131513922000000000" />
<file name="tartan-01.html" server="ftp.turkcadcam.net" local="131514135097632744" remote="131513922000000000" />
<file name="tasarimmed-01.html" server="ftp.turkcadcam.net" local="131514135097852737" remote="131513922000000000" />
<file name="tekateknik-03.html" server="ftp.turkcadcam.net" local="131514135098072944" remote="131513922000000000" />
<file name="tekno-tasarim-10.html" server="ftp.turkcadcam.net" local="131514135098473300" remote="131513922000000000" />
<file name="tekno-tasarim-11.html" server="ftp.turkcadcam.net" local="131514135098673437" remote="131513922000000000" />
<file name="tekyaz-01.html" server="ftp.turkcadcam.net" local="131514135098873575" remote="131513922000000000" />
<file name="tekyaz-02.html" server="ftp.turkcadcam.net" local="131514135099063761" remote="131513922000000000" />
<file name="tekyaz-03.html" server="ftp.turkcadcam.net" local="131514135099283835" remote="131513922000000000" />
<file name="tekyaz-04.html" server="ftp.turkcadcam.net" local="131514135099484011" remote="131513922000000000" />
<file name="tekyaz-05.html" server="ftp.turkcadcam.net" local="131514135099694207" remote="131513922000000000" />
<file name="tolerans-kalip-03.html" server="ftp.turkcadcam.net" local="131514135100084479" remote="131513922000000000" />
<file name="tolerans-kalip-04.html" server="ftp.turkcadcam.net" local="131514135100284620" remote="131513922000000000" />
<file name="tolerans-kalip-05.html" server="ftp.turkcadcam.net" local="131514135100474712" remote="131513922000000000" />
<file name="tpd-01.html" server="ftp.turkcadcam.net" local="131514135100674858" remote="131513922000000000" />
<file name="trexta-04.html" server="ftp.turkcadcam.net" local="131514135100884883" remote="131513922000000000" />
<file name="tunahan-01.html" server="ftp.turkcadcam.net" local="131514135101875755" remote="131513922000000000" />
<file name="tunalimited-01.html" server="ftp.turkcadcam.net" local="131514135102075901" remote="131513922000000000" />
<file name="turalerdeniz-01.html" server="ftp.turkcadcam.net" local="131514135102276042" remote="131513922000000000" />
<file name="ucbilek-01.html" server="ftp.turkcadcam.net" local="131514135102466168" remote="131513922000000000" />
<file name="ucgen-02.html" server="ftp.turkcadcam.net" local="131514135102666310" remote="131513922000000000" />
<file name="ucgen-03.html" server="ftp.turkcadcam.net" local="131514135102866452" remote="131513922000000000" />
<file name="ucgen-04.html" server="ftp.turkcadcam.net" local="131514135103066598" remote="131513922000000000" />
<file name="ucuncubinyil-01.html" server="ftp.turkcadcam.net" local="131514135103456865" remote="131513922000000000" />
<file name="ugur-plastik-01.html" server="ftp.turkcadcam.net" local="131514135103857153" remote="131513922000000000" />
<file name="ugur-plastik-02.html" server="ftp.turkcadcam.net" local="131514135104057247" remote="131513922000000000" />
<file name="ukd-01.html" server="ftp.turkcadcam.net" local="131514135104257432" remote="131513922000000000" />
<file name="unalmodel-01.html" server="ftp.turkcadcam.net" local="131514135104457531" remote="131513922000000000" />
<file name="unifit-01.html" server="ftp.turkcadcam.net" local="131514135104667675" remote="131513922000000000" />
<file name="universal-01.html" server="ftp.turkcadcam.net" local="131514135104868035" remote="131513922000000000" />
<file name="ural-01.html" server="ftp.turkcadcam.net" local="131514135105458282" remote="131513922000000000" />
<file name="uygur-01.html" server="ftp.turkcadcam.net" local="131514135105648416" remote="131513922000000000" />
<file name="vhs-01.html" server="ftp.turkcadcam.net" local="131514135106378775" remote="131513922000000000" />
<file name="vk-01.html" server="ftp.turkcadcam.net" local="131514135106578912" remote="131513922000000000" />
<file name="walter-01.html" server="ftp.turkcadcam.net" local="131514135106779054" remote="131513922000000000" />
<file name="walter-02.html" server="ftp.turkcadcam.net" local="131514135106969184" remote="131513922000000000" />
<file name="walter-03.html" server="ftp.turkcadcam.net" local="131514135107169330" remote="131513922000000000" />
<file name="X-01.html" server="ftp.turkcadcam.net" local="131514135107759863" remote="131513922600000000" />
<file name="X-02.html" server="ftp.turkcadcam.net" local="131514135107959885" remote="131513922600000000" />
<file name="X-03.html" server="ftp.turkcadcam.net" local="131514135108150191" remote="131513922600000000" />
<file name="X-04.html" server="ftp.turkcadcam.net" local="131514135108340321" remote="131513922600000000" />
<file name="X-05.html" server="ftp.turkcadcam.net" local="131514135108520461" remote="131513922600000000" />
<file name="yavuztorna-01.html" server="ftp.turkcadcam.net" local="131514135109100859" remote="131513922600000000" />
<file name="yildiz-kalip-01.html" server="ftp.turkcadcam.net" local="131514135109491144" remote="131513922600000000" />
<file name="yildiz-plastik-01.html" server="ftp.turkcadcam.net" local="131514135109691239" remote="131513922600000000" />
<file name="zamak-metal-01.html" server="ftp.turkcadcam.net" local="131514135110661968" remote="131513922600000000" />
<file name="zirve-yazilim-01.html" server="ftp.turkcadcam.net" local="131514135110862110" remote="131513922600000000" />
<file name="sato-plastik-05.html" server="ftp.turkcadcam.net" local="131514135094860786" remote="131513922000000000" />
<file name="ucuncubinyil-02.html" server="ftp.turkcadcam.net" local="131514135103666847" remote="131513922000000000" />
<file name="protosis-01.html" server="ftp.turkcadcam.net" local="131514135089067956" remote="131513922000000000" />
<file name="ntg-plastik-04.html" server="ftp.turkcadcam.net" local="131514135081259703" remote="131513921400000000" />
<file name="polikim-01.html" server="ftp.turkcadcam.net" local="131514135088667852" remote="131513922000000000" />
<file name="kale-havacilik-14.html" server="ftp.turkcadcam.net" local="131514135070236146" remote="131513921400000000" />
<file name="arkatasarim-01.html" server="ftp.turkcadcam.net" local="131514135042282115" remote="131513920200000000" />
<file name="makkalip-04.html" server="ftp.turkcadcam.net" local="131514135073548481" remote="131513921400000000" />
<file name="semmak-05.html" server="ftp.turkcadcam.net" local="131514135096391827" remote="131513922000000000" />
<file name="nikken-10.html" server="ftp.turkcadcam.net" local="131514135079738636" remote="131513921400000000" />
<file name="ucgen-05.html" server="ftp.turkcadcam.net" local="131514135103256724" remote="131513922000000000" />
<file name="orsaproje-03.html" server="ftp.turkcadcam.net" local="131514135082220392" remote="131513921400000000" />
<file name="yudo-01.html" server="ftp.turkcadcam.net" local="131514135110471663" remote="131513922600000000" />
<file name="eksen-03.html" server="ftp.turkcadcam.net" local="131514135058286073" remote="131513920800000000" />
<file name="yudo-01-iptal.html" server="ftp.turkcadcam.net" local="131514135110081558" remote="131513922600000000" />
<file name="yudo-01-iptal2.html" server="ftp.turkcadcam.net" local="131514135110271688" remote="131513922600000000" />
<file name="kalipsan-01.html" server="ftp.turkcadcam.net" local="131514135071386952" remote="131513921400000000" />
<file name="truemed-01.html" server="ftp.turkcadcam.net" local="131514135101075175" remote="131513922000000000" />
<file name="X-06.html" server="ftp.turkcadcam.net" local="131514135108710605" remote="131513922600000000" />
<file name="altunorak-04.html" server="ftp.turkcadcam.net" local="131514135040701646" remote="131513920200000000" />
<file name="ocplastik-01.html" server="ftp.turkcadcam.net" local="131514135081639977" remote="131513921400000000" />
<file name="hakanunlu-02.html" server="ftp.turkcadcam.net" local="131514135063156443" remote="131513920800000000" />
<file name="izoleelektrik-01.html" server="ftp.turkcadcam.net" local="131514135066393426" remote="131513920800000000" />
<file name="veyselkutuklu-01.html" server="ftp.turkcadcam.net" local="131514135105888428" remote="131513922000000000" />
<file name="nikken-11.html" server="ftp.turkcadcam.net" local="131514135079928766" remote="131513921400000000" />
<file name="bagbek-01.html" server="ftp.turkcadcam.net" local="131514135044673803" remote="131513920200000000" />
<file name="yenasoft-01.html" server="ftp.turkcadcam.net" local="131514135109301010" remote="131513922600000000" />
<file name="wiz-01.html" server="ftp.turkcadcam.net" local="131514135107569776" remote="131513922600000000" />
<file name="veyselkutuklu-02.html" server="ftp.turkcadcam.net" local="131514135106128705" remote="131513922000000000" />
<file name="cdsmakina-01.html" server="ftp.turkcadcam.net" local="131514135052451992" remote="131513920800000000" />
<file name="unterm-01.html" server="ftp.turkcadcam.net" local="131514135105258101" remote="131513922000000000" />
<file name="armada-03.html" server="ftp.turkcadcam.net" local="131514135042892380" remote="131513920200000000" />
<file name="ozaycamkalip-01.html" server="ftp.turkcadcam.net" local="131514135083220938" remote="131513921400000000" />
<file name="walter-04.html" server="ftp.turkcadcam.net" local="131514135107369591" remote="131513922000000000" />
<file name="kalipsan-02.html" server="ftp.turkcadcam.net" local="131514135071587098" remote="131513921400000000" />
<file name="orsaproje-04.html" server="ftp.turkcadcam.net" local="131514135082410535" remote="131513921400000000" />
<file name="tanmodel-01.html" server="ftp.turkcadcam.net" local="131514135097422556" remote="131513922000000000" />
<file name="marotomasyon-01.html" server="ftp.turkcadcam.net" local="131514135075089576" remote="131513921400000000" />
<file name="X-07.html" server="ftp.turkcadcam.net" local="131514135108900731" remote="131513922600000000" />
<file name="sato-plastik-06.html" server="ftp.turkcadcam.net" local="131514135095060885" remote="131513922000000000" />
<file name="sarigozoglu-01.html" server="ftp.turkcadcam.net" local="131514135093889937" remote="131513922000000000" />
<file name="geenta-01.html" server="ftp.turkcadcam.net" local="131514135061965558" remote="131513920800000000" />
<file name="ykk-01.html" server="ftp.turkcadcam.net" local="131514135109891423" remote="131513922600000000" />
<file name="taegutec-01.html" server="ftp.turkcadcam.net" local="131514135097222410" remote="131513922000000000" />
<file name="pimtasplastik-01.html" server="ftp.turkcadcam.net" local="131514135084772035" remote="131513921400000000" />
<file name="tsk-01.html" server="ftp.turkcadcam.net" local="131514135101285290" remote="131513922000000000" />
<file name="akyuzlu-01.html" server="ftp.turkcadcam.net" local="131514135038018393" remote="131513920200000000" />
<file name="masel-01.html" server="ftp.turkcadcam.net" local="131514135075279706" remote="131513921400000000" />
<file name="sato-plastik-07.html" server="ftp.turkcadcam.net" local="131514135095271081" remote="131513922000000000" />
<file name="teknikgrup-01.html" server="ftp.turkcadcam.net" local="131514135098263151" remote="131513922000000000" />
<file name="orsaproje-05.html" server="ftp.turkcadcam.net" local="131514135082610510" remote="131513921400000000" />
<file name="orsaproje-06.html" server="ftp.turkcadcam.net" local="131514135082820654" remote="131513921400000000" />
<file name="universal-03.html" server="ftp.turkcadcam.net" local="131514135105058003" remote="131513922000000000" />
<file name="delcam-03.html" server="ftp.turkcadcam.net" local="131514135054963607" remote="131513920800000000" />
<file name="factorh-01.html" server="ftp.turkcadcam.net" local="131514135060544556" remote="131513920800000000" />
<file name="elfjet-03.html" server="ftp.turkcadcam.net" local="131514135059103537" remote="131513920800000000" />
<file name="bures-02.html" server="ftp.turkcadcam.net" local="131514135049326160" remote="131513920800000000" />
<file name="hktm-01.html" server="ftp.turkcadcam.net" local="131514135064156997" remote="131513920800000000" />
<file name="plast-met-09.html" server="ftp.turkcadcam.net" local="131514135087359879" remote="131513922000000000" />
<file name="4cmedikal-09.html" server="ftp.turkcadcam.net" local="131514135035966941" remote="131513920200000000" />
<file name="kale-havacilik-15.html" server="ftp.turkcadcam.net" local="131514135070436287" remote="131513921400000000" />
<file name="puntomakina-01.html" server="ftp.turkcadcam.net" local="131514135089258266" remote="131513922000000000" />
<file name="makkalip-05.html" server="ftp.turkcadcam.net" local="131514135073738616" remote="131513921400000000" />
<file name="dekortools-03.html" server="ftp.turkcadcam.net" local="131514135054353188" remote="131513920800000000" />
<file name="revizyon-makina-05.html" server="ftp.turkcadcam.net" local="131514135091859932" remote="131513922000000000" />
<file name="bures-03.html" server="ftp.turkcadcam.net" local="131514135049516299" remote="131513920800000000" />
<file name="tekyaz-06.html" server="ftp.turkcadcam.net" local="131514135099894511" remote="131513922000000000" />
<file name="merkad-02.html" server="ftp.turkcadcam.net" local="131514135076040249" remote="131513921400000000" />
<file name="cimtas-01.html" server="ftp.turkcadcam.net" local="131514135052652146" remote="131513920800000000" />
<file name="bozokmakina-01.html" server="ftp.turkcadcam.net" local="131514135048545616" remote="131513920800000000" />
<file name="durmusogluplastik-01-iptal.html" server="ftp.turkcadcam.net" local="131514135056815079" remote="131513920800000000" />
<file name="durmusogluplastik-01.html" server="ftp.turkcadcam.net" local="131514135057015050" remote="131513920800000000" />
<file name="nikken-12.html" server="ftp.turkcadcam.net" local="131514135080118905" remote="131513921400000000" />
<file name="makkalip-06.html" server="ftp.turkcadcam.net" local="131514135073928755" remote="131513921400000000" />
<file name="ttaf-01.html" server="ftp.turkcadcam.net" local="131514135101475420" remote="131513922000000000" />
<file name="polimatek-01.html" server="ftp.turkcadcam.net" local="131514135088867942" remote="131513922000000000" />
<file name="ttaf-02.html" server="ftp.turkcadcam.net" local="131514135101675609" remote="131513922000000000" />
<file name="makkalip-02.html" server="ftp.turkcadcam.net" local="131514135073158214" remote="131513921400000000" />
<file name="laurus-01.html" server="ftp.turkcadcam.net" local="131514135072577790" remote="131513921400000000" />
<file name="4cmedikal-09-EN.html" server="ftp.turkcadcam.net" local="131514135035776806" remote="131513920200000000" />
<file name="kalekalip-pe-q.doc" server="ftp.turkcadcam.net" local="128286127433750000" remote="131513921400000000" />
<file name="maselset-01-iptal.html" server="ftp.turkcadcam.net" local="131514135075469845" remote="131513921400000000" />
<file name="0-at.gif" server="server251.web-hosting.com/public_html/" local="128459977294218750" remote="131535160200000000" />
<file name="3b-dizayn-02.html" server="server251.web-hosting.com/public_html/" local="131514135033315064" remote="131535160200000000" />
<file name="3dcadcam-02-old.html" server="server251.web-hosting.com/public_html/" local="131514135033505199" remote="131535160200000000" />
<file name="3dcadcam-02.html" server="server251.web-hosting.com/public_html/" local="131514135033695333" remote="131535160200000000" />
<file name="3ds-01.html" server="server251.web-hosting.com/public_html/" local="131514135033895539" remote="131535160200000000" />
<file name="4cmedikal-01.html" server="server251.web-hosting.com/public_html/" local="131514135034085609" remote="131535160200000000" />
<file name="4cmedikal-02.html" server="server251.web-hosting.com/public_html/" local="131514135034275744" remote="131535160200000000" />
<file name="4cmedikal-03.html" server="server251.web-hosting.com/public_html/" local="131514135034465878" remote="131535160200000000" />
<file name="4cmedikal-04.html" server="server251.web-hosting.com/public_html/" local="131514135034656013" remote="131535160200000000" />
<file name="4cmedikal-05.html" server="server251.web-hosting.com/public_html/" local="131514135034836140" remote="131535160200000000" />
<file name="4cmedikal-06.html" server="server251.web-hosting.com/public_html/" local="131514135035026275" remote="131535160200000000" />
<file name="4cmedikal-07.html" server="server251.web-hosting.com/public_html/" local="131514135035216410" remote="131535160200000000" />
<file name="4cmedikal-08-iptal.html" server="server251.web-hosting.com/public_html/" local="131514135035406548" remote="131535160200000000" />
<file name="4cmedikal-08.html" server="server251.web-hosting.com/public_html/" local="131514135035586672" remote="131535160200000000" />
<file name="4cmedikal-09-EN.html" server="server251.web-hosting.com/public_html/" local="131514135035776806" remote="131535160200000000" />
<file name="4cmedikal-09.html" server="server251.web-hosting.com/public_html/" local="131514135035966941" remote="131535160200000000" />
<file name="aat-01.html" server="server251.web-hosting.com/public_html/" local="131514135036147068" remote="131535160200000000" />
<file name="aba-otomotiv-01.html" server="server251.web-hosting.com/public_html/" local="131514135036327196" remote="131535160200000000" />
<file name="abcadcam-01.html" server="server251.web-hosting.com/public_html/" local="131514135036517330" remote="131535160200000000" />
<file name="abcadcam-02.html" server="server251.web-hosting.com/public_html/" local="131514135036707465" remote="131535160200000000" />
<file name="abigem-kocaeli-01.html" server="server251.web-hosting.com/public_html/" local="131514135036897599" remote="131535160200000000" />
<file name="ACMT-Makine-01.html" server="server251.web-hosting.com/public_html/" local="131514135037087734" remote="131535160200000000" />
<file name="adam-01.html" server="server251.web-hosting.com/public_html/" local="131514135037277868" remote="131535160200000000" />
<file name="adim-01.html" server="server251.web-hosting.com/public_html/" local="131514135037457996" remote="131535160200000000" />
<file name="akana-01.html" server="server251.web-hosting.com/public_html/" local="131514135037638123" remote="131535160200000000" />
<file name="akmetal-01.html" server="server251.web-hosting.com/public_html/" local="131514135037828258" remote="131535160200000000" />
<file name="akyuzlu-01.html" server="server251.web-hosting.com/public_html/" local="131514135038018393" remote="131535160200000000" />
<file name="albakalip-03.html" server="server251.web-hosting.com/public_html/" local="131514135038419972" remote="131535160200000000" />
<file name="aldes-01.html" server="server251.web-hosting.com/public_html/" local="131514135038610115" remote="131535160200000000" />
<file name="alfa-01.html" server="server251.web-hosting.com/public_html/" local="131514135038810261" remote="131535160200000000" />
<file name="alpar-01.html" server="server251.web-hosting.com/public_html/" local="131514135038990384" remote="131535160200000000" />
<file name="alpar-02.html" server="server251.web-hosting.com/public_html/" local="131514135039180527" remote="131535160200000000" />
<file name="altanhidrolik-01.html" server="server251.web-hosting.com/public_html/" local="131514135039370649" remote="131535160200000000" />
<file name="altar-08.html" server="server251.web-hosting.com/public_html/" local="131514135039570799" remote="131535160200000000" />
<file name="altar-09.html" server="server251.web-hosting.com/public_html/" local="131514135039760925" remote="131535160200000000" />
<file name="altin-kristal-01.html" server="server251.web-hosting.com/public_html/" local="131514135039941052" remote="131535160200000000" />
<file name="altunorak-01.html" server="server251.web-hosting.com/public_html/" local="131514135040141258" remote="131535160200000000" />
<file name="altunorak-02.html" server="server251.web-hosting.com/public_html/" local="131514135040321321" remote="131535160200000000" />
<file name="altunorak-03.html" server="server251.web-hosting.com/public_html/" local="131514135040511456" remote="131535160200000000" />
<file name="altunorak-04.html" server="server251.web-hosting.com/public_html/" local="131514135040701646" remote="131535160200000000" />
<file name="anarotomotiv-01.html" server="server251.web-hosting.com/public_html/" local="131514135040881718" remote="131535160200000000" />
<file name="ar-is-01.html" server="server251.web-hosting.com/public_html/" local="131514135041071853" remote="131535160200000000" />
<file name="ar-is-02.html" server="server251.web-hosting.com/public_html/" local="131514135041271998" remote="131535160200000000" />
<file name="ar-is-03.html" server="server251.web-hosting.com/public_html/" local="131514135041482151" remote="131535160200000000" />
<file name="araslube-01.html" server="server251.web-hosting.com/public_html/" local="131514135041682242" remote="131535160200000000" />
<file name="argemuhendislik-06.html" server="server251.web-hosting.com/public_html/" local="131514135041882430" remote="131535160200000000" />
<file name="aritas-01.html" server="server251.web-hosting.com/public_html/" local="131514135042081978" remote="131535160200000000" />
<file name="arkatasarim-01.html" server="server251.web-hosting.com/public_html/" local="131514135042282115" remote="131535160200000000" />
<file name="armada-01.html" server="server251.web-hosting.com/public_html/" local="131514135042482257" remote="131535160200000000" />
<file name="armada-02.html" server="server251.web-hosting.com/public_html/" local="131514135042692410" remote="131535160200000000" />
<file name="armada-03.html" server="server251.web-hosting.com/public_html/" local="131514135042892380" remote="131535160200000000" />
<file name="armadental-01.html" server="server251.web-hosting.com/public_html/" local="131514135043082686" remote="131535160200000000" />
<file name="arpas-02.html" server="server251.web-hosting.com/public_html/" local="131514135043282828" remote="131535160200000000" />
<file name="array-01.html" server="server251.web-hosting.com/public_html/" local="131514135043482973" remote="131535160800000000" />
<file name="artikalip-01.html" server="server251.web-hosting.com/public_html/" local="131514135043683111" remote="131535160800000000" />
<file name="atadizayn-01.html" server="server251.web-hosting.com/public_html/" local="131514135043883248" remote="131535160800000000" />
<file name="atalan-makine-04.html" server="server251.web-hosting.com/public_html/" local="131514135044083390" remote="131535160800000000" />
<file name="avrotas-03.html" server="server251.web-hosting.com/public_html/" local="131514135044283536" remote="131535160800000000" />
<file name="avrotas-04.html" server="server251.web-hosting.com/public_html/" local="131514135044473666" remote="131535160800000000" />
<file name="bagbek-01.html" server="server251.web-hosting.com/public_html/" local="131514135044673803" remote="131535160800000000" />
<file name="baykarmakina-02.html" server="server251.web-hosting.com/public_html/" local="131514135044883781" remote="131535160800000000" />
<file name="bdtyazilim-01.html" server="server251.web-hosting.com/public_html/" local="131514135045084111" remote="131535160800000000" />
<file name="bdtyazilim-02.html" server="server251.web-hosting.com/public_html/" local="131514135045284235" remote="131535160800000000" />
<file name="bedir-01.html" server="server251.web-hosting.com/public_html/" local="131514135045494311" remote="131535160800000000" />
<file name="bedir-02.html" server="server251.web-hosting.com/public_html/" local="131514135045704533" remote="131535160800000000" />
<file name="bemis-01.html" server="server251.web-hosting.com/public_html/" local="131514135045914682" remote="131535160800000000" />
<file name="bias-02.html" server="server251.web-hosting.com/public_html/" local="131514135046114832" remote="131535160800000000" />
<file name="bicakcilar-01.html" server="server251.web-hosting.com/public_html/" local="131514135046314969" remote="131535160800000000" />
<file name="bimex-04.html" server="server251.web-hosting.com/public_html/" local="131514135046523980" remote="131535160800000000" />
<file name="bogazici-yazilim-03.html" server="server251.web-hosting.com/public_html/" local="131514135046724323" remote="131535160800000000" />
<file name="bogazici-yazilim-04.html" server="server251.web-hosting.com/public_html/" local="131514135046924464" remote="131535160800000000" />
<file name="bogazici-yazilim-05.html" server="server251.web-hosting.com/public_html/" local="131514135047134566" remote="131535160800000000" />
<file name="boyut-cnc-01.html" server="server251.web-hosting.com/public_html/" local="131514135047334759" remote="131535160800000000" />
<file name="boyut-cnc-02.html" server="server251.web-hosting.com/public_html/" local="131514135047534901" remote="131535160800000000" />
<file name="boyut-cnc-03.html" server="server251.web-hosting.com/public_html/" local="131514135047745002" remote="131535160800000000" />
<file name="boyut-cnc-04.html" server="server251.web-hosting.com/public_html/" local="131514135047945187" remote="131535160800000000" />
<file name="boyut-cnc-05.html" server="server251.web-hosting.com/public_html/" local="131514135048145328" remote="131535160800000000" />
<file name="bozkurtmodel-01.html" server="server251.web-hosting.com/public_html/" local="131514135048345432" remote="131535160800000000" />
<file name="bozokmakina-01.html" server="server251.web-hosting.com/public_html/" local="131514135048545616" remote="131535160800000000" />
<file name="BSA-bilg-01.html" server="server251.web-hosting.com/public_html/" local="131514135048745749" remote="131535160800000000" />
<file name="BSA-bilg-02.html" server="server251.web-hosting.com/public_html/" local="131514135048935884" remote="131535160800000000" />
<file name="bures-01.html" server="server251.web-hosting.com/public_html/" local="131514135049135876" remote="131535160800000000" />
<file name="bures-02.html" server="server251.web-hosting.com/public_html/" local="131514135049326160" remote="131535160800000000" />
<file name="bures-03.html" server="server251.web-hosting.com/public_html/" local="131514135049516299" remote="131535160800000000" />
<file name="cadem-09.html" server="server251.web-hosting.com/public_html/" local="131514135049716440" remote="131535160800000000" />
<file name="cadem-10.html" server="server251.web-hosting.com/public_html/" local="131514135049906575" remote="131535160800000000" />
<file name="cadem-11.html" server="server251.web-hosting.com/public_html/" local="131514135050220417" remote="131535160800000000" />
<file name="cadem-12.html" server="server251.web-hosting.com/public_html/" local="131514135050410547" remote="131535160800000000" />
<file name="cadem-13.html" server="server251.web-hosting.com/public_html/" local="131514135050600677" remote="131535160800000000" />
<file name="cadem-14.html" server="server251.web-hosting.com/public_html/" local="131514135050790816" remote="131535160800000000" />
<file name="cadem-15.html" server="server251.web-hosting.com/public_html/" local="131514135050990953" remote="131535160800000000" />
<file name="cadem-16.html" server="server251.web-hosting.com/public_html/" local="131514135051230965" remote="131535160800000000" />
<file name="cadem-17.html" server="server251.web-hosting.com/public_html/" local="131514135051451121" remote="131535160800000000" />
<file name="cagcadcam-03.html" server="server251.web-hosting.com/public_html/" local="131514135051661355" remote="131535160800000000" />
<file name="cagcadcam-04.html" server="server251.web-hosting.com/public_html/" local="131514135051861527" remote="131535160800000000" />
<file name="cagri-end-08.html" server="server251.web-hosting.com/public_html/" local="131514135052061707" remote="131535160800000000" />
<file name="cagri-end-09.html" server="server251.web-hosting.com/public_html/" local="131514135052251850" remote="131535160800000000" />
<file name="cdsmakina-01.html" server="server251.web-hosting.com/public_html/" local="131514135052451992" remote="131535160800000000" />
<file name="cimtas-01.html" server="server251.web-hosting.com/public_html/" local="131514135052652146" remote="131535160800000000" />
<file name="cozumkalip-01.html" server="server251.web-hosting.com/public_html/" local="131514135052862295" remote="131535160800000000" />
<file name="cozumkalip-02.html" server="server251.web-hosting.com/public_html/" local="131514135053062445" remote="131535160800000000" />
<file name="cozumkalip-03.html" server="server251.web-hosting.com/public_html/" local="131514135053292510" remote="131535160800000000" />
<file name="dahirinsaat-01.html" server="server251.web-hosting.com/public_html/" local="131514135053512708" remote="131535160800000000" />
<file name="dalelektronik-01.html" server="server251.web-hosting.com/public_html/" local="131514135053722895" remote="131535160800000000" />
<file name="dekortools-01.html" server="server251.web-hosting.com/public_html/" local="131514135053943000" remote="131535160800000000" />
<file name="dekortools-02.html" server="server251.web-hosting.com/public_html/" local="131514135054143141" remote="131535160800000000" />
<file name="dekortools-03.html" server="server251.web-hosting.com/public_html/" local="131514135054353188" remote="131535160800000000" />
<file name="delcam-01.html" server="server251.web-hosting.com/public_html/" local="131514135054563375" remote="131535160800000000" />
<file name="delcam-02.html" server="server251.web-hosting.com/public_html/" local="131514135054763465" remote="131535160800000000" />
<file name="delcam-03.html" server="server251.web-hosting.com/public_html/" local="131514135054963607" remote="131535160800000000" />
<file name="dema3000-01.html" server="server251.web-hosting.com/public_html/" local="131514135055173760" remote="131535160800000000" />
<file name="desa-01.html" server="server251.web-hosting.com/public_html/" local="131514135055383896" remote="131535160800000000" />
<file name="dostel-01.html" server="server251.web-hosting.com/public_html/" local="131514135055584037" remote="131535160800000000" />
<file name="dreambox-01.html" server="server251.web-hosting.com/public_html/" local="131514135055784307" remote="131535160800000000" />
<file name="dunyakalip-01.html" server="server251.web-hosting.com/public_html/" local="131514135055984445" remote="131535161400000000" />
<file name="durmusogluplastik-01-iptal.html" server="server251.web-hosting.com/public_html/" local="131514135056815079" remote="131535161400000000" />
<file name="durmusogluplastik-01.html" server="server251.web-hosting.com/public_html/" local="131514135057015050" remote="131535161400000000" />
<file name="efeendustri-01.html" server="server251.web-hosting.com/public_html/" local="131514135057235330" remote="131535161400000000" />
<file name="ekerplastik-01.html" server="server251.web-hosting.com/public_html/" local="131514135057445483" remote="131535161400000000" />
<file name="ekinler-03-old.html" server="server251.web-hosting.com/public_html/" local="131514135057655632" remote="131535161400000000" />
<file name="ekinler-03.html" server="server251.web-hosting.com/public_html/" local="131514135057875834" remote="131535161400000000" />
<file name="eksen-02.html" server="server251.web-hosting.com/public_html/" local="131514135058075929" remote="131535161400000000" />
<file name="eksen-03.html" server="server251.web-hosting.com/public_html/" local="131514135058286073" remote="131535161400000000" />
<file name="eksenkalip-01.html" server="server251.web-hosting.com/public_html/" local="131514135058486215" remote="131535161400000000" />
<file name="elfjet-01.html" server="server251.web-hosting.com/public_html/" local="131514135058686361" remote="131535161400000000" />
<file name="elfjet-02.html" server="server251.web-hosting.com/public_html/" local="131514135058893388" remote="131535161400000000" />
<file name="elfjet-03.html" server="server251.web-hosting.com/public_html/" local="131514135059103537" remote="131535161400000000" />
<file name="elmaplastik-01.html" server="server251.web-hosting.com/public_html/" local="131514135059303670" remote="131535161400000000" />
<file name="ender-01.html" server="server251.web-hosting.com/public_html/" local="131514135059513874" remote="131535161400000000" />
<file name="enformak-01.html" server="server251.web-hosting.com/public_html/" local="131514135059723976" remote="131535161400000000" />
<file name="enformak-02.html" server="server251.web-hosting.com/public_html/" local="131514135059924109" remote="131535161400000000" />
<file name="ermakina-01.html" server="server251.web-hosting.com/public_html/" local="131514135060134262" remote="131535161400000000" />
<file name="evreko-01.html" server="server251.web-hosting.com/public_html/" local="131514135060334399" remote="131535161400000000" />
<file name="factorh-01.html" server="server251.web-hosting.com/public_html/" local="131514135060544556" remote="131535161400000000" />
<file name="fatih-univ-01.html" server="server251.web-hosting.com/public_html/" local="131514135060734734" remote="131535161400000000" />
<file name="fetih-plastik-07.html" server="server251.web-hosting.com/public_html/" local="131514135060924860" remote="131535161400000000" />
<file name="fetih-plastik-08.html" server="server251.web-hosting.com/public_html/" local="131514135061134974" remote="131535161400000000" />
<file name="fibrobeton-01.html" server="server251.web-hosting.com/public_html/" local="131514135061345123" remote="131535161400000000" />
<file name="ge-mtc-03.html" server="server251.web-hosting.com/public_html/" local="131514135061555267" remote="131535161400000000" />
<file name="ge-mtc-04.html" server="server251.web-hosting.com/public_html/" local="131514135061765574" remote="131535161400000000" />
<file name="geenta-01.html" server="server251.web-hosting.com/public_html/" local="131514135061965558" remote="131535161400000000" />
<file name="girginler-01.html" server="server251.web-hosting.com/public_html/" local="131514135062165699" remote="131535161400000000" />
<file name="girginler-02.html" server="server251.web-hosting.com/public_html/" local="131514135062365888" remote="131535161400000000" />
<file name="glassco-01.html" server="server251.web-hosting.com/public_html/" local="131514135062565983" remote="131535161400000000" />
<file name="glassco-02.html" server="server251.web-hosting.com/public_html/" local="131514135062766120" remote="131535161400000000" />
<file name="hakanunlu-01.html" server="server251.web-hosting.com/public_html/" local="131514135062966304" remote="131535161400000000" />
<file name="hakanunlu-02.html" server="server251.web-hosting.com/public_html/" local="131514135063156443" remote="131535161400000000" />
<file name="hexagon-01.html" server="server251.web-hosting.com/public_html/" local="131514135063356589" remote="131535161400000000" />
<file name="hidroser-01.html" server="server251.web-hosting.com/public_html/" local="131514135063556821" remote="131535161400000000" />
<file name="hidrotam-02.html" server="server251.web-hosting.com/public_html/" local="131514135063756864" remote="131535161400000000" />
<file name="hidrotam-03.html" server="server251.web-hosting.com/public_html/" local="131514135063957014" remote="131535161400000000" />
<file name="hktm-01.html" server="server251.web-hosting.com/public_html/" local="131514135064156997" remote="131535161400000000" />
<file name="hofmann-turk-01.html" server="server251.web-hosting.com/public_html/" local="131514135064377329" remote="131535161400000000" />
<file name="hofmann-turk-02.html" server="server251.web-hosting.com/public_html/" local="131514135064597318" remote="131535161400000000" />
<file name="imren-plastik-01.html" server="server251.web-hosting.com/public_html/" local="131514135064807625" remote="131535161400000000" />
<file name="imren-plastik-02.html" server="server251.web-hosting.com/public_html/" local="131514135065007698" remote="131535161400000000" />
<file name="inores-01.html" server="server251.web-hosting.com/public_html/" local="131514135065207797" remote="131535161400000000" />
<file name="intexis-01.html" server="server251.web-hosting.com/public_html/" local="131514135065402682" remote="131535161400000000" />
<file name="islem-01.html" server="server251.web-hosting.com/public_html/" local="131514135065602820" remote="131535161400000000" />
<file name="islem-02.html" server="server251.web-hosting.com/public_html/" local="131514135065812968" remote="131535161400000000" />
<file name="islem-03.html" server="server251.web-hosting.com/public_html/" local="131514135066003150" remote="131535161400000000" />
<file name="ivesta-01.html" server="server251.web-hosting.com/public_html/" local="131514135066203253" remote="131535161400000000" />
<file name="izoleelektrik-01.html" server="server251.web-hosting.com/public_html/" local="131514135066393426" remote="131535161400000000" />
<file name="kaanmakina-02.html" server="server251.web-hosting.com/public_html/" local="131514135066593568" remote="131535161400000000" />
<file name="kaban-01.html" server="server251.web-hosting.com/public_html/" local="131514135066783694" remote="131535161400000000" />
<file name="kahraman-kalip-03.html" server="server251.web-hosting.com/public_html/" local="131514135066973833" remote="131535161400000000" />
<file name="kahraman-kalip-04.html" server="server251.web-hosting.com/public_html/" local="131514135067163967" remote="131535161400000000" />
<file name="kahraman-kalip-05.html" server="server251.web-hosting.com/public_html/" local="131514135067354098" remote="131535161400000000" />
<file name="kahraman-kalip-06.html" server="server251.web-hosting.com/public_html/" local="131514135067544228" remote="131535161400000000" />
<file name="kale-havacilik-01.html" server="server251.web-hosting.com/public_html/" local="131514135067734367" remote="131535161400000000" />
<file name="kale-havacilik-02.html" server="server251.web-hosting.com/public_html/" local="131514135067924501" remote="131535162000000000" />
<file name="kale-havacilik-03.html" server="server251.web-hosting.com/public_html/" local="131514135068114636" remote="131535162000000000" />
<file name="kale-havacilik-04.html" server="server251.web-hosting.com/public_html/" local="131514135068304766" remote="131535162000000000" />
<file name="kale-havacilik-05.html" server="server251.web-hosting.com/public_html/" local="131514135068494905" remote="131535162000000000" />
<file name="kale-havacilik-06.html" server="server251.web-hosting.com/public_html/" local="131514135068685044" remote="131535162000000000" />
<file name="kale-havacilik-07.html" server="server251.web-hosting.com/public_html/" local="131514135068885185" remote="131535162000000000" />
<file name="kale-havacilik-08.html" server="server251.web-hosting.com/public_html/" local="131514135069075320" remote="131535162000000000" />
<file name="kale-havacilik-09.html" server="server251.web-hosting.com/public_html/" local="131514135069275457" remote="131535162000000000" />
<file name="kale-havacilik-10.html" server="server251.web-hosting.com/public_html/" local="131514135069465596" remote="131535162000000000" />
<file name="kale-havacilik-11.html" server="server251.web-hosting.com/public_html/" local="131514135069665734" remote="131535162000000000" />
<file name="kale-havacilik-12.html" server="server251.web-hosting.com/public_html/" local="131514135069855872" remote="131535162000000000" />
<file name="kale-havacilik-13.html" server="server251.web-hosting.com/public_html/" local="131514135070046003" remote="131535162000000000" />
<file name="kale-havacilik-14.html" server="server251.web-hosting.com/public_html/" local="131514135070236146" remote="131535162000000000" />
<file name="kale-havacilik-15.html" server="server251.web-hosting.com/public_html/" local="131514135070436287" remote="131535162000000000" />
<file name="kalekalip-havacilik-07.html" server="server251.web-hosting.com/public_html/" local="131514135070616406" remote="131535162000000000" />
<file name="kalekalip-havacilik-08.html" server="server251.web-hosting.com/public_html/" local="131514135070816552" remote="131535162000000000" />
<file name="kalekalip-pe-q.doc" server="server251.web-hosting.com/public_html/" local="128286127433750000" remote="131535162000000000" />
<file name="kalip-destek-01.html" server="server251.web-hosting.com/public_html/" local="131514135071006687" remote="131535162000000000" />
<file name="kalip-destek-02.html" server="server251.web-hosting.com/public_html/" local="131514135071196817" remote="131535162000000000" />
<file name="kalipsan-01.html" server="server251.web-hosting.com/public_html/" local="131514135071386952" remote="131535162000000000" />
<file name="kalipsan-02.html" server="server251.web-hosting.com/public_html/" local="131514135071587098" remote="131535162000000000" />
<file name="kemsan-01.html" server="server251.web-hosting.com/public_html/" local="131514135071777236" remote="131535162000000000" />
<file name="kismetcnc-01.html" server="server251.web-hosting.com/public_html/" local="131514135071967362" remote="131535162000000000" />
<file name="kizilca-01.html" server="server251.web-hosting.com/public_html/" local="131514135072167513" remote="131535162000000000" />
<file name="komet-01.html" server="server251.web-hosting.com/public_html/" local="131514135072367658" remote="131535162000000000" />
<file name="laurus-01.html" server="server251.web-hosting.com/public_html/" local="131514135072577790" remote="131535162000000000" />
<file name="magmatasarim-01.html" server="server251.web-hosting.com/public_html/" local="131514135072777919" remote="131535162000000000" />
<file name="makkalip-01.html" server="server251.web-hosting.com/public_html/" local="131514135072968071" remote="131535162000000000" />
<file name="makkalip-02.html" server="server251.web-hosting.com/public_html/" local="131514135073158214" remote="131535162000000000" />
<file name="makkalip-03.html" server="server251.web-hosting.com/public_html/" local="131514135073358347" remote="131535162000000000" />
<file name="makkalip-04.html" server="server251.web-hosting.com/public_html/" local="131514135073548481" remote="131535162000000000" />
<file name="makkalip-05.html" server="server251.web-hosting.com/public_html/" local="131514135073738616" remote="131535162000000000" />
<file name="makkalip-06.html" server="server251.web-hosting.com/public_html/" local="131514135073928755" remote="131535162000000000" />
<file name="makyay-01.html" server="server251.web-hosting.com/public_html/" local="131514135074118885" remote="131535162000000000" />
<file name="manus-01.html" server="server251.web-hosting.com/public_html/" local="131514135074319027" remote="131535162000000000" />
<file name="markalip-01.html" server="server251.web-hosting.com/public_html/" local="131514135074509165" remote="131535162000000000" />
<file name="markalip-02.html" server="server251.web-hosting.com/public_html/" local="131514135074709260" remote="131535162000000000" />
<file name="markalip-03.html" server="server251.web-hosting.com/public_html/" local="131514135074899442" remote="131535162000000000" />
<file name="marotomasyon-01.html" server="server251.web-hosting.com/public_html/" local="131514135075089576" remote="131535162000000000" />
<file name="masel-01.html" server="server251.web-hosting.com/public_html/" local="131514135075279706" remote="131535162000000000" />
<file name="maselset-01-iptal.html" server="server251.web-hosting.com/public_html/" local="131514135075469845" remote="131535162000000000" />
<file name="maysat-02.html" server="server251.web-hosting.com/public_html/" local="131514135075659976" remote="131535162000000000" />
<file name="mekano-01.html" server="server251.web-hosting.com/public_html/" local="131514135075860169" remote="131535162000000000" />
<file name="merkad-02.html" server="server251.web-hosting.com/public_html/" local="131514135076040249" remote="131535162000000000" />
<file name="mfk-01.html" server="server251.web-hosting.com/public_html/" local="131514135076240386" remote="131535162000000000" />
<file name="mfs-01.html" server="server251.web-hosting.com/public_html/" local="131514135076430521" remote="131535162000000000" />
<file name="mfs-02.html" server="server251.web-hosting.com/public_html/" local="131514135076630663" remote="131535162000000000" />
<file name="mfs-03.html" server="server251.web-hosting.com/public_html/" local="131514135076820797" remote="131535162000000000" />
<file name="milimetrik-01.html" server="server251.web-hosting.com/public_html/" local="131514135077020943" remote="131535162000000000" />
<file name="modus-01.html" server="server251.web-hosting.com/public_html/" local="131514135077211078" remote="131535162000000000" />
<file name="modus-02.html" server="server251.web-hosting.com/public_html/" local="131514135077411048" remote="131535162000000000" />
<file name="mt-01.html" server="server251.web-hosting.com/public_html/" local="131514135077601358" remote="131535162000000000" />
<file name="mtn-01.html" server="server251.web-hosting.com/public_html/" local="131514135077791488" remote="131535162000000000" />
<file name="mubitek-01.html" server="server251.web-hosting.com/public_html/" local="131514135077981623" remote="131535162000000000" />
<file name="murat-01.html" server="server251.web-hosting.com/public_html/" local="131514135078161746" remote="131535162000000000" />
<file name="neksus-01.html" server="server251.web-hosting.com/public_html/" local="131514135078361888" remote="131535162000000000" />
<file name="nesne-emt-01.html" server="server251.web-hosting.com/public_html/" local="131514135078562072" remote="131535162000000000" />
<file name="nikken-05.html" server="server251.web-hosting.com/public_html/" local="131514135078762150" remote="131535162000000000" />
<file name="nikken-06.html" server="server251.web-hosting.com/public_html/" local="131514135078962330" remote="131535162000000000" />
<file name="nikken-07.html" server="server251.web-hosting.com/public_html/" local="131514135079152443" remote="131535162000000000" />
<file name="nikken-08.html" server="server251.web-hosting.com/public_html/" local="131514135079342586" remote="131535162600000000" />
<file name="nikken-09.html" server="server251.web-hosting.com/public_html/" local="131514135079542732" remote="131535162600000000" />
<file name="nikken-10.html" server="server251.web-hosting.com/public_html/" local="131514135079738636" remote="131535162600000000" />
<file name="nikken-11.html" server="server251.web-hosting.com/public_html/" local="131514135079928766" remote="131535162600000000" />
<file name="nikken-12.html" server="server251.web-hosting.com/public_html/" local="131514135080118905" remote="131535162600000000" />
<file name="ninamedikal-01.html" server="server251.web-hosting.com/public_html/" local="131514135080309035" remote="131535162600000000" />
<file name="nkg-01.html" server="server251.web-hosting.com/public_html/" local="131514135080499174" remote="131535162600000000" />
<file name="ntg-plastik-01.html" server="server251.web-hosting.com/public_html/" local="131514135080679301" remote="131535162600000000" />
<file name="ntg-plastik-02.html" server="server251.web-hosting.com/public_html/" local="131514135080879439" remote="131535162600000000" />
<file name="ntg-plastik-03.html" server="server251.web-hosting.com/public_html/" local="131514135081069577" remote="131535162600000000" />
<file name="ntg-plastik-04.html" server="server251.web-hosting.com/public_html/" local="131514135081259703" remote="131535162600000000" />
<file name="numarine-01.html" server="server251.web-hosting.com/public_html/" local="131514135081449851" remote="131535162600000000" />
<file name="ocplastik-01.html" server="server251.web-hosting.com/public_html/" local="131514135081639977" remote="131535162600000000" />
<file name="orsaproje-01.html" server="server251.web-hosting.com/public_html/" local="131514135081830116" remote="131535162600000000" />
<file name="orsaproje-02.html" server="server251.web-hosting.com/public_html/" local="131514135082020250" remote="131535162600000000" />
<file name="orsaproje-03.html" server="server251.web-hosting.com/public_html/" local="131514135082220392" remote="131535162600000000" />
<file name="orsaproje-04.html" server="server251.web-hosting.com/public_html/" local="131514135082410535" remote="131535162600000000" />
<file name="orsaproje-05.html" server="server251.web-hosting.com/public_html/" local="131514135082610510" remote="131535162600000000" />
<file name="orsaproje-06.html" server="server251.web-hosting.com/public_html/" local="131514135082820654" remote="131535162600000000" />
<file name="ostim-01.html" server="server251.web-hosting.com/public_html/" local="131514135083020800" remote="131535162600000000" />
<file name="ozaycamkalip-01.html" server="server251.web-hosting.com/public_html/" local="131514135083220938" remote="131535162600000000" />
<file name="ozmikromak-01.html" server="server251.web-hosting.com/public_html/" local="131514135083421075" remote="131535162600000000" />
<file name="ozugurlu-makina-02.html" server="server251.web-hosting.com/public_html/" local="131514135083611214" remote="131535162600000000" />
<file name="pals-01.html" server="server251.web-hosting.com/public_html/" local="131514135083801353" remote="131535162600000000" />
<file name="pals-02.html" server="server251.web-hosting.com/public_html/" local="131514135083991483" remote="131535162600000000" />
<file name="parametrik-makina-01.html" server="server251.web-hosting.com/public_html/" local="131514135084191624" remote="131535162600000000" />
<file name="petrotec-01.html" server="server251.web-hosting.com/public_html/" local="131514135084381759" remote="131535162600000000" />
<file name="pimeks-01.html" server="server251.web-hosting.com/public_html/" local="131514135084581896" remote="131535162600000000" />
<file name="pimtasplastik-01.html" server="server251.web-hosting.com/public_html/" local="131514135084772035" remote="131535162600000000" />
<file name="piramtek-01-old.html" server="server251.web-hosting.com/public_html/" local="131514135084972177" remote="131535162600000000" />
<file name="piramtek-01.html" server="server251.web-hosting.com/public_html/" local="131514135085172319" remote="131535162600000000" />
<file name="pirimer-01.html" server="server251.web-hosting.com/public_html/" local="131514135085362453" remote="131535162600000000" />
<file name="plascam-01.html" server="server251.web-hosting.com/public_html/" local="131514135085552588" remote="131535162600000000" />
<file name="plascam-02.html" server="server251.web-hosting.com/public_html/" local="131514135085752729" remote="131535162600000000" />
<file name="plascam-03.html" server="server251.web-hosting.com/public_html/" local="131514135085952875" remote="131535162600000000" />
<file name="plascam-04.html" server="server251.web-hosting.com/public_html/" local="131514135086153004" remote="131535162600000000" />
<file name="plascam-05.html" server="server251.web-hosting.com/public_html/" local="131514135086353317" remote="131535162600000000" />
<file name="plascam-06.html" server="server251.web-hosting.com/public_html/" local="131514135086563470" remote="131535162600000000" />
<file name="plascam-07.html" server="server251.web-hosting.com/public_html/" local="131514135086763432" remote="131535162600000000" />
<file name="plascam-08.html" server="server251.web-hosting.com/public_html/" local="131514135086953742" remote="131535162600000000" />
<file name="plast-met-08.html" server="server251.web-hosting.com/public_html/" local="131514135087163895" remote="131535162600000000" />
<file name="plast-met-09.html" server="server251.web-hosting.com/public_html/" local="131514135087359879" remote="131535162600000000" />
<file name="platin-kalip-01.html" server="server251.web-hosting.com/public_html/" local="131514135087589927" remote="131535162600000000" />
<file name="platin-kalip-02.html" server="server251.web-hosting.com/public_html/" local="131514135087820085" remote="131535162600000000" />
<file name="plus-education-01.html" server="server251.web-hosting.com/public_html/" local="131514135088070263" remote="131535162600000000" />
<file name="plus90-01.html" server="server251.web-hosting.com/public_html/" local="131514135088270391" remote="131535162600000000" />
<file name="pobusan-01.html" server="server251.web-hosting.com/public_html/" local="131514135088477517" remote="131535162600000000" />
<file name="polikim-01.html" server="server251.web-hosting.com/public_html/" local="131514135088667852" remote="131535162600000000" />
<file name="polimatek-01.html" server="server251.web-hosting.com/public_html/" local="131514135088867942" remote="131535162600000000" />
<file name="protosis-01.html" server="server251.web-hosting.com/public_html/" local="131514135089067956" remote="131535162600000000" />
<file name="puntomakina-01.html" server="server251.web-hosting.com/public_html/" local="131514135089258266" remote="131535162600000000" />
<file name="putzmeister-01.html" server="server251.web-hosting.com/public_html/" local="131514135089458241" remote="131535162600000000" />
<file name="rasem-01.html" server="server251.web-hosting.com/public_html/" local="131514135089648550" remote="131535162600000000" />
<file name="rayba-01.html" server="server251.web-hosting.com/public_html/" local="131514135089848645" remote="131535162600000000" />
<file name="redoks-01.html" server="server251.web-hosting.com/public_html/" local="131514135090048654" remote="131535162600000000" />
<file name="redoks-02.html" server="server251.web-hosting.com/public_html/" local="131514135090258799" remote="131535162600000000" />
<file name="remicnc-01.html" server="server251.web-hosting.com/public_html/" local="131514135090458940" remote="131535162600000000" />
<file name="remicnc-02.html" server="server251.web-hosting.com/public_html/" local="131514135090649079" remote="131535162600000000" />
<file name="remicnc-03.html" server="server251.web-hosting.com/public_html/" local="131514135090869231" remote="131535162600000000" />
<file name="revizyon-makina-01.html" server="server251.web-hosting.com/public_html/" local="131514135091059365" remote="131535163200000000" />
<file name="revizyon-makina-02.html" server="server251.web-hosting.com/public_html/" local="131514135091259507" remote="131535163200000000" />
<file name="revizyon-makina-03.html" server="server251.web-hosting.com/public_html/" local="131514135091459653" remote="131535163200000000" />
<file name="revizyon-makina-04.html" server="server251.web-hosting.com/public_html/" local="131514135091659790" remote="131535163200000000" />
<file name="revizyon-makina-05.html" server="server251.web-hosting.com/public_html/" local="131514135091859932" remote="131535163200000000" />
<file name="romak-01.html" server="server251.web-hosting.com/public_html/" local="131514135092050066" remote="131535163200000000" />
<file name="rozmas-03.html" server="server251.web-hosting.com/public_html/" local="131514135092250212" remote="131535163200000000" />
<file name="rsa-01.html" server="server251.web-hosting.com/public_html/" local="131514135092440342" remote="131535163200000000" />
<file name="safaksan-02.html" server="server251.web-hosting.com/public_html/" local="131514135092660498" remote="131535163200000000" />
<file name="sahinoglu-01.html" server="server251.web-hosting.com/public_html/" local="131514135092870647" remote="131535163200000000" />
<file name="sahinoglu-02.html" server="server251.web-hosting.com/public_html/" local="131514135093070789" remote="131535163200000000" />
<file name="sanaltasarim-01.html" server="server251.web-hosting.com/public_html/" local="131514135093279466" remote="131535163200000000" />
<file name="sanaltasarim-02.html" server="server251.web-hosting.com/public_html/" local="131514135093479762" remote="131535163200000000" />
<file name="sanaltasarim-03.html" server="server251.web-hosting.com/public_html/" local="131514135093689910" remote="131535163200000000" />
<file name="sarigozoglu-01.html" server="server251.web-hosting.com/public_html/" local="131514135093889937" remote="131535163200000000" />
<file name="sato-plastik-02.html" server="server251.web-hosting.com/public_html/" local="131514135094090254" remote="131535163200000000" />
<file name="sato-plastik-03.html" server="server251.web-hosting.com/public_html/" local="131514135094450449" remote="131535163200000000" />
<file name="sato-plastik-04.html" server="server251.web-hosting.com/public_html/" local="131514135094660593" remote="131535163200000000" />
<file name="sato-plastik-05.html" server="server251.web-hosting.com/public_html/" local="131514135094860786" remote="131535163200000000" />
<file name="sato-plastik-06.html" server="server251.web-hosting.com/public_html/" local="131514135095060885" remote="131535163200000000" />
<file name="sato-plastik-07.html" server="server251.web-hosting.com/public_html/" local="131514135095271081" remote="131535163200000000" />
<file name="sazcilar-01.html" server="server251.web-hosting.com/public_html/" local="131514135095471175" remote="131535163200000000" />
<file name="sema-02.html" server="server251.web-hosting.com/public_html/" local="131514135095701214" remote="131535163200000000" />
<file name="semmak-03.html" server="server251.web-hosting.com/public_html/" local="131514135095931510" remote="131535163200000000" />
<file name="semmak-04.html" server="server251.web-hosting.com/public_html/" local="131514135096171757" remote="131535163200000000" />
<file name="semmak-05.html" server="server251.web-hosting.com/public_html/" local="131514135096391827" remote="131535163200000000" />
<file name="sistemmak-01.html" server="server251.web-hosting.com/public_html/" local="131514135096601976" remote="131535163200000000" />
<file name="solidteknoloji-01.html" server="server251.web-hosting.com/public_html/" local="131514135096812176" remote="131535163200000000" />
<file name="star-01.html" server="server251.web-hosting.com/public_html/" local="131514135097012266" remote="131535163200000000" />
<file name="taegutec-01.html" server="server251.web-hosting.com/public_html/" local="131514135097222410" remote="131535163200000000" />
<file name="tanmodel-01.html" server="server251.web-hosting.com/public_html/" local="131514135097422556" remote="131535163200000000" />
<file name="tartan-01.html" server="server251.web-hosting.com/public_html/" local="131514135097632744" remote="131535163200000000" />
<file name="tasarimmed-01.html" server="server251.web-hosting.com/public_html/" local="131514135097852737" remote="131535163200000000" />
<file name="tekateknik-03.html" server="server251.web-hosting.com/public_html/" local="131514135098072944" remote="131535163200000000" />
<file name="teknikgrup-01.html" server="server251.web-hosting.com/public_html/" local="131514135098263151" remote="131535163200000000" />
<file name="tekno-tasarim-10.html" server="server251.web-hosting.com/public_html/" local="131514135098473300" remote="131535163200000000" />
<file name="tekno-tasarim-11.html" server="server251.web-hosting.com/public_html/" local="131514135098673437" remote="131535163200000000" />
<file name="tekyaz-01.html" server="server251.web-hosting.com/public_html/" local="131514135098873575" remote="131535163200000000" />
<file name="tekyaz-02.html" server="server251.web-hosting.com/public_html/" local="131514135099063761" remote="131535163200000000" />
<file name="tekyaz-03.html" server="server251.web-hosting.com/public_html/" local="131514135099283835" remote="131535163200000000" />
<file name="tekyaz-04.html" server="server251.web-hosting.com/public_html/" local="131514135099484011" remote="131535163200000000" />
<file name="tekyaz-05.html" server="server251.web-hosting.com/public_html/" local="131514135099694207" remote="131535163200000000" />
<file name="tekyaz-06.html" server="server251.web-hosting.com/public_html/" local="131514135099894511" remote="131535163200000000" />
<file name="tolerans-kalip-03.html" server="server251.web-hosting.com/public_html/" local="131514135100084479" remote="131535163200000000" />
<file name="tolerans-kalip-04.html" server="server251.web-hosting.com/public_html/" local="131514135100284620" remote="131535163200000000" />
<file name="tolerans-kalip-05.html" server="server251.web-hosting.com/public_html/" local="131514135100474712" remote="131535163200000000" />
<file name="tpd-01.html" server="server251.web-hosting.com/public_html/" local="131514135100674858" remote="131535163200000000" />
<file name="trexta-04.html" server="server251.web-hosting.com/public_html/" local="131514135100884883" remote="131535163200000000" />
<file name="truemed-01.html" server="server251.web-hosting.com/public_html/" local="131514135101075175" remote="131535163200000000" />
<file name="tsk-01.html" server="server251.web-hosting.com/public_html/" local="131514135101285290" remote="131535163200000000" />
<file name="ttaf-01.html" server="server251.web-hosting.com/public_html/" local="131514135101475420" remote="131535163200000000" />
<file name="ttaf-02.html" server="server251.web-hosting.com/public_html/" local="131514135101675609" remote="131535163200000000" />
<file name="tunahan-01.html" server="server251.web-hosting.com/public_html/" local="131514135101875755" remote="131535163200000000" />
<file name="tunalimited-01.html" server="server251.web-hosting.com/public_html/" local="131514135102075901" remote="131535163200000000" />
<file name="turalerdeniz-01.html" server="server251.web-hosting.com/public_html/" local="131514135102276042" remote="131535163200000000" />
<file name="ucbilek-01.html" server="server251.web-hosting.com/public_html/" local="131514135102466168" remote="131535163200000000" />
<file name="ucgen-02.html" server="server251.web-hosting.com/public_html/" local="131514135102666310" remote="131535163200000000" />
<file name="ucgen-03.html" server="server251.web-hosting.com/public_html/" local="131514135102866452" remote="131535163200000000" />
<file name="ucgen-04.html" server="server251.web-hosting.com/public_html/" local="131514135103066598" remote="131535163200000000" />
<file name="ucgen-05.html" server="server251.web-hosting.com/public_html/" local="131514135103256724" remote="131535163200000000" />
<file name="ucuncubinyil-01.html" server="server251.web-hosting.com/public_html/" local="131514135103456865" remote="131535163200000000" />
<file name="ucuncubinyil-02.html" server="server251.web-hosting.com/public_html/" local="131514135103666847" remote="131535163800000000" />
<file name="ugur-plastik-01.html" server="server251.web-hosting.com/public_html/" local="131514135103857153" remote="131535163800000000" />
<file name="ugur-plastik-02.html" server="server251.web-hosting.com/public_html/" local="131514135104057247" remote="131535163800000000" />
<file name="ukd-01.html" server="server251.web-hosting.com/public_html/" local="131514135104257432" remote="131535163800000000" />
<file name="unalmodel-01.html" server="server251.web-hosting.com/public_html/" local="131514135104457531" remote="131535163800000000" />
<file name="unifit-01.html" server="server251.web-hosting.com/public_html/" local="131514135104667675" remote="131535163800000000" />
<file name="universal-01.html" server="server251.web-hosting.com/public_html/" local="131514135104868035" remote="131535163800000000" />
<file name="universal-03.html" server="server251.web-hosting.com/public_html/" local="131514135105058003" remote="131535163800000000" />
<file name="unterm-01.html" server="server251.web-hosting.com/public_html/" local="131514135105258101" remote="131535163800000000" />
<file name="ural-01.html" server="server251.web-hosting.com/public_html/" local="131514135105458282" remote="131535163800000000" />
<file name="uygur-01.html" server="server251.web-hosting.com/public_html/" local="131514135105648416" remote="131535163800000000" />
<file name="veyselkutuklu-01.html" server="server251.web-hosting.com/public_html/" local="131514135105888428" remote="131535163800000000" />
<file name="veyselkutuklu-02.html" server="server251.web-hosting.com/public_html/" local="131514135106128705" remote="131535163800000000" />
<file name="vhs-01.html" server="server251.web-hosting.com/public_html/" local="131514135106378775" remote="131535163800000000" />
<file name="vk-01.html" server="server251.web-hosting.com/public_html/" local="131514135106578912" remote="131535163800000000" />
<file name="walter-01.html" server="server251.web-hosting.com/public_html/" local="131514135106779054" remote="131535163800000000" />
<file name="walter-02.html" server="server251.web-hosting.com/public_html/" local="131514135106969184" remote="131535163800000000" />
<file name="walter-03.html" server="server251.web-hosting.com/public_html/" local="131514135107169330" remote="131535163800000000" />
<file name="walter-04.html" server="server251.web-hosting.com/public_html/" local="131514135107369591" remote="131535163800000000" />
<file name="wiz-01.html" server="server251.web-hosting.com/public_html/" local="131514135107569776" remote="131535163800000000" />
<file name="X-01.html" server="server251.web-hosting.com/public_html/" local="131514135107759863" remote="131535163800000000" />
<file name="X-02.html" server="server251.web-hosting.com/public_html/" local="131514135107959885" remote="131535163800000000" />
<file name="X-03.html" server="server251.web-hosting.com/public_html/" local="131514135108150191" remote="131535163800000000" />
<file name="X-04.html" server="server251.web-hosting.com/public_html/" local="131514135108340321" remote="131535163800000000" />
<file name="X-05.html" server="server251.web-hosting.com/public_html/" local="131514135108520461" remote="131535163800000000" />
<file name="X-06.html" server="server251.web-hosting.com/public_html/" local="131514135108710605" remote="131535163800000000" />
<file name="X-07.html" server="server251.web-hosting.com/public_html/" local="131514135108900731" remote="131535163800000000" />
<file name="yavuztorna-01.html" server="server251.web-hosting.com/public_html/" local="131514135109100859" remote="131535163800000000" />
<file name="yenasoft-01.html" server="server251.web-hosting.com/public_html/" local="131514135109301010" remote="131535163800000000" />
<file name="yildiz-kalip-01.html" server="server251.web-hosting.com/public_html/" local="131514135109491144" remote="131535163800000000" />
<file name="yildiz-plastik-01.html" server="server251.web-hosting.com/public_html/" local="131514135109691239" remote="131535163800000000" />
<file name="ykk-01.html" server="server251.web-hosting.com/public_html/" local="131514135109891423" remote="131535163800000000" />
<file name="yudo-01-iptal.html" server="server251.web-hosting.com/public_html/" local="131514135110081558" remote="131535163800000000" />
<file name="yudo-01-iptal2.html" server="server251.web-hosting.com/public_html/" local="131514135110271688" remote="131535163800000000" />
<file name="yudo-01.html" server="server251.web-hosting.com/public_html/" local="131514135110471663" remote="131535163800000000" />
<file name="zamak-metal-01.html" server="server251.web-hosting.com/public_html/" local="131514135110661968" remote="131535163800000000" />
<file name="zirve-yazilim-01.html" server="server251.web-hosting.com/public_html/" local="131514135110862110" remote="131535163800000000" />
<file name="proaktifteknoloji-01.html" server="server251.web-hosting.com/public_html/" local="131562424009804933" remote="131562207600000000" />
<file name="dural-makina-03-deleted.html" server="server251.web-hosting.com/www/" local="131514135056404746" remote="132346822200000000" />
<file name="dural-makina-04-deleted.html" server="server251.web-hosting.com/www/" local="131514135056614891" remote="132346822200000000" />
</dwsync>