<?xml version="1.0" encoding="utf-8" ?>
<dwsync>
<file name="index.html" server="ftp.turkcadcam.net" local="131514798038525439" remote="131514590400000000" />
<file name="01.gif" server="server251.web-hosting.com/public_html/" local="128389188152187500" remote="131535365400000000" />
<file name="02.png" server="server251.web-hosting.com/public_html/" local="128389188152812500" remote="131535365400000000" />
<file name="03-t.png" server="server251.web-hosting.com/public_html/" local="128389189657812500" remote="131535365400000000" />
<file name="03.png" server="server251.web-hosting.com/public_html/" local="128389188153906250" remote="131535365400000000" />
<file name="04.jpg" server="server251.web-hosting.com/public_html/" local="128389191134375000" remote="131535365400000000" />
<file name="05.png" server="server251.web-hosting.com/public_html/" local="128389188155312500" remote="131535365400000000" />
<file name="index.html" server="server251.web-hosting.com/public_html/" local="131529627232241689" remote="131535365400000000" />
</dwsync>