<?xml version="1.0" encoding="utf-8" ?>
<dwsync>
<file name="index.html" server="ftp.turkcadcam.net" local="131514797824038811" remote="131514589200000000" />
<file name="index2.html" server="ftp.turkcadcam.net" local="131514797824908371" remote="131514589200000000" />
<file name="index3.html" server="ftp.turkcadcam.net" local="131514797825788079" remote="131514589200000000" />
<file name="01.gif" server="server251.web-hosting.com/public_html/" local="128221465676093750" remote="131535338400000000" />
<file name="02.png" server="server251.web-hosting.com/public_html/" local="128221465676093750" remote="131535338400000000" />
<file name="03.gif" server="server251.web-hosting.com/public_html/" local="128221465677031250" remote="131535338400000000" />
<file name="04.gif" server="server251.web-hosting.com/public_html/" local="128232817863281250" remote="131535338400000000" />
<file name="05-2.gif" server="server251.web-hosting.com/public_html/" local="128232814227031250" remote="131535338400000000" />
<file name="05.gif" server="server251.web-hosting.com/public_html/" local="128232814966875000" remote="131535338400000000" />
<file name="06.gif" server="server251.web-hosting.com/public_html/" local="128221465683437500" remote="131535338400000000" />
<file name="07.gif" server="server251.web-hosting.com/public_html/" local="128221465683906250" remote="131535338400000000" />
<file name="08.gif" server="server251.web-hosting.com/public_html/" local="128232814590468750" remote="131535338400000000" />
<file name="09-2.gif" server="server251.web-hosting.com/public_html/" local="128232816247187500" remote="131535338400000000" />
<file name="09.gif" server="server251.web-hosting.com/public_html/" local="128232815291250000" remote="131535338400000000" />
<file name="10.gif" server="server251.web-hosting.com/public_html/" local="128221465687656250" remote="131535338400000000" />
<file name="11-t.gif" server="server251.web-hosting.com/public_html/" local="128233409854218750" remote="131535338400000000" />
<file name="11.gif" server="server251.web-hosting.com/public_html/" local="128221465688281250" remote="131535338400000000" />
<file name="12.gif" server="server251.web-hosting.com/public_html/" local="128221465688750000" remote="131535338400000000" />
<file name="13.gif" server="server251.web-hosting.com/public_html/" local="128221465689218750" remote="131535338400000000" />
<file name="14.gif" server="server251.web-hosting.com/public_html/" local="128221465689531250" remote="131535338400000000" />
<file name="15.gif" server="server251.web-hosting.com/public_html/" local="128233396747187500" remote="131535338400000000" />
<file name="16.jpg" server="server251.web-hosting.com/public_html/" local="128232818497343750" remote="131535338400000000" />
<file name="formul1.gif" server="server251.web-hosting.com/public_html/" local="128233925275156250" remote="131535338400000000" />
<file name="formul2.gif" server="server251.web-hosting.com/public_html/" local="128233924984531250" remote="131535338400000000" />
<file name="formul3.gif" server="server251.web-hosting.com/public_html/" local="128233924382812500" remote="131535338400000000" />
<file name="index.html" server="server251.web-hosting.com/public_html/" local="131529627003439997" remote="131535338400000000" />
<file name="index2.html" server="server251.web-hosting.com/public_html/" local="131529627004453080" remote="131535338400000000" />
<file name="index3.html" server="server251.web-hosting.com/public_html/" local="131529627005533878" remote="131535338400000000" />
<file name="Jant-Dinamik-Darbe-Testi-Modellemesi.doc" server="server251.web-hosting.com/public_html/" local="128220609657340000" remote="131535339000000000" />
</dwsync>