<?xml version="1.0" encoding="utf-8" ?>
<dwsync>
<file name="index.html" server="ftp.turkcadcam.net" local="130316635507776720" remote="130316383800000000" />
<file name="3b_logo.jpg" server="server251.web-hosting.com/public_html/" local="129860582084257146" remote="131535143400000000" />
<file name="electrode.jpg" server="server251.web-hosting.com/public_html/" local="129860582018550576" remote="131535143400000000" />
<file name="fptn.jpg" server="server251.web-hosting.com/public_html/" local="129862963362010041" remote="131535143400000000" />
<file name="index.html" server="server251.web-hosting.com/public_html/" local="130316635507776720" remote="131535143400000000" />
<file name="index2.html" server="server251.web-hosting.com/public_html/" local="129860667902268183" remote="131535143400000000" />
<file name="mold-t.jpg" server="server251.web-hosting.com/public_html/" local="129862961931285041" remote="131535143400000000" />
<file name="mold1.jpg" server="server251.web-hosting.com/public_html/" local="129860581695818306" remote="131535143400000000" />
<file name="progress.jpg" server="server251.web-hosting.com/public_html/" local="129860581785557279" remote="131535143400000000" />
<file name="ts_logo.jpg" server="server251.web-hosting.com/public_html/" local="129860581492778004" remote="131535143400000000" />
</dwsync>