<?xml version="1.0" encoding="utf-8" ?>
<dwsync>
<file name="cd-cover-01.png" server="server251.web-hosting.com/public_html/" local="127861819800000000" remote="131534626200000000" />
<file name="kapak-01.gif" server="server251.web-hosting.com/public_html/" local="127861820400000000" remote="131534626200000000" />
<file name="tasarim-teknoloji-dergisi-sponsor.jpg" server="server251.web-hosting.com/public_html/" local="127904158200000000" remote="131534626200000000" />
<file name="tu-pano-1-t.jpg" server="server251.web-hosting.com/public_html/" local="127861820400000000" remote="131534626200000000" />
<file name="tu-pano-1.jpg" server="server251.web-hosting.com/public_html/" local="127861820400000000" remote="131534626200000000" />
<file name="tu-pano-2-t.jpg" server="server251.web-hosting.com/public_html/" local="127861820400000000" remote="131534626200000000" />
<file name="tu-pano-2.jpg" server="server251.web-hosting.com/public_html/" local="127861820400000000" remote="131534626200000000" />
<file name="tu-pano-3-t.jpg" server="server251.web-hosting.com/public_html/" local="127861820400000000" remote="131534626200000000" />
<file name="tu-pano-3.jpg" server="server251.web-hosting.com/public_html/" local="127861820400000000" remote="131534626200000000" />
<file name="tu-pano-4-t.jpg" server="server251.web-hosting.com/public_html/" local="127861821000000000" remote="131534626200000000" />
<file name="tu-pano-4.jpg" server="server251.web-hosting.com/public_html/" local="127861821000000000" remote="131534626200000000" />
<file name="uu-pano-t.jpg" server="server251.web-hosting.com/public_html/" local="127891776600000000" remote="131534626200000000" />
<file name="uu-pano.jpg" server="server251.web-hosting.com/public_html/" local="127891776600000000" remote="131534626200000000" />
</dwsync>