<?xml version="1.0" encoding="utf-8" ?>
<dwsync>
<file name="index.html" server="ftp.turkcadcam.net" local="131514796825765362" remote="131514584400000000" />
<file name="index2.html" server="ftp.turkcadcam.net" local="131514796827106764" remote="131514584400000000" />
<file name="index3.html" server="ftp.turkcadcam.net" local="131514796828802225" remote="131514584400000000" />
<file name="ankara-takim-t.jpg" server="server251.web-hosting.com/public_html/" local="128790203973437500" remote="131534932200000000" />
<file name="ankara-takim.jpg" server="server251.web-hosting.com/public_html/" local="128790203973906250" remote="131534932200000000" />
<file name="ankara-yaris-t.jpg" server="server251.web-hosting.com/public_html/" local="128790203974218750" remote="131534932200000000" />
<file name="ankara-yaris.jpg" server="server251.web-hosting.com/public_html/" local="128790203974687500" remote="131534932200000000" />
<file name="bilinmeyen-takim-t.jpg" server="server251.web-hosting.com/public_html/" local="128790203975000000" remote="131534932200000000" />
<file name="bilinmeyen-takim.jpg" server="server251.web-hosting.com/public_html/" local="128790203975468750" remote="131534932200000000" />
<file name="bilinmeyen2-takim-t.jpg" server="server251.web-hosting.com/public_html/" local="128790203975625000" remote="131534932200000000" />
<file name="bilinmeyen2-takim.jpg" server="server251.web-hosting.com/public_html/" local="128790203975937500" remote="131534932200000000" />
<file name="coskun-lisesi-t.jpg" server="server251.web-hosting.com/public_html/" local="128790203976250000" remote="131534932200000000" />
<file name="coskun-lisesi.jpg" server="server251.web-hosting.com/public_html/" local="128790203976562500" remote="131534932200000000" />
<file name="deu-takim-t.jpg" server="server251.web-hosting.com/public_html/" local="128790203976718750" remote="131534932200000000" />
<file name="deu-takim.jpg" server="server251.web-hosting.com/public_html/" local="128790203977031250" remote="131534932200000000" />
<file name="deu-yaris-t.jpg" server="server251.web-hosting.com/public_html/" local="128790203977343750" remote="131534932200000000" />
<file name="deu-yaris.jpg" server="server251.web-hosting.com/public_html/" local="128790203978125000" remote="131534932200000000" />
<file name="gazi-takim-t.jpg" server="server251.web-hosting.com/public_html/" local="128790203978593750" remote="131534932200000000" />
<file name="gazi-takim.jpg" server="server251.web-hosting.com/public_html/" local="128790203978906250" remote="131534932200000000" />
<file name="gyte-sabanci-takim-t.jpg" server="server251.web-hosting.com/public_html/" local="128790203979375000" remote="131534932200000000" />
<file name="gyte-sabanci-takim.jpg" server="server251.web-hosting.com/public_html/" local="128790203979687500" remote="131534932200000000" />
<file name="hasat-takim-t.jpg" server="server251.web-hosting.com/public_html/" local="128790203979843750" remote="131534932200000000" />
<file name="hasat-takim.jpg" server="server251.web-hosting.com/public_html/" local="128790203980312500" remote="131534932200000000" />
<file name="hasat-yaris-t.jpg" server="server251.web-hosting.com/public_html/" local="128790203980625000" remote="131534932200000000" />
<file name="hasat-yaris.jpg" server="server251.web-hosting.com/public_html/" local="128790203980937500" remote="131534932200000000" />
<file name="hazirlik.jpg" server="server251.web-hosting.com/public_html/" local="128790203981250000" remote="131534932200000000" />
<file name="index.html" server="server251.web-hosting.com/public_html/" local="131529626477003232" remote="131534932200000000" />
<file name="index2.html" server="server251.web-hosting.com/public_html/" local="131529626478048000" remote="131534932200000000" />
<file name="index3.html" server="server251.web-hosting.com/public_html/" local="131529626479068952" remote="131534932200000000" />
<file name="kocaeli-gayret-takim-t.jpg" server="server251.web-hosting.com/public_html/" local="128790203981406250" remote="131534932200000000" />
<file name="kocaeli-gayret-takim.jpg" server="server251.web-hosting.com/public_html/" local="128790203981875000" remote="131534932200000000" />
<file name="kocaeli-gayret-yaris-t.jpg" server="server251.web-hosting.com/public_html/" local="128790203982031250" remote="131534932200000000" />
<file name="kocaeli-gayret-yaris.jpg" server="server251.web-hosting.com/public_html/" local="128790203982343750" remote="131534932200000000" />
<file name="kocaeli-takim-t.jpg" server="server251.web-hosting.com/public_html/" local="128790203982656250" remote="131534932200000000" />
<file name="kocaeli-takim.jpg" server="server251.web-hosting.com/public_html/" local="128790203983906250" remote="131534932800000000" />
<file name="kocaeli-yaris-t.jpg" server="server251.web-hosting.com/public_html/" local="128790203984062500" remote="131534932800000000" />
<file name="kocaeli-yaris.jpg" server="server251.web-hosting.com/public_html/" local="128790203984375000" remote="131534932800000000" />
<file name="mese3.jpg" server="server251.web-hosting.com/public_html/" local="128790203984843750" remote="131534932800000000" />
<file name="mese4-t.jpg" server="server251.web-hosting.com/public_html/" local="128790203985000000" remote="131534932800000000" />
<file name="mese4.jpg" server="server251.web-hosting.com/public_html/" local="128790203985468750" remote="131534932800000000" />
<file name="odtu-takim-t.jpg" server="server251.web-hosting.com/public_html/" local="128790203985625000" remote="131534932800000000" />
<file name="odtu-takim.jpg" server="server251.web-hosting.com/public_html/" local="128790203986093750" remote="131534932800000000" />
<file name="odtu-yaris-t.jpg" server="server251.web-hosting.com/public_html/" local="128790203986250000" remote="131534932800000000" />
<file name="odtu-yaris.jpg" server="server251.web-hosting.com/public_html/" local="128790203986718750" remote="131534932800000000" />
<file name="ort-frame-ss.gif" server="server251.web-hosting.com/public_html/" local="128790203986875000" remote="131534932800000000" />
<file name="ort-kupa.jpg" server="server251.web-hosting.com/public_html/" local="128790203987812500" remote="131534932800000000" />
<file name="ort-takim.jpg" server="server251.web-hosting.com/public_html/" local="128790203988125000" remote="131534932800000000" />
<file name="ort-yaris.jpg" server="server251.web-hosting.com/public_html/" local="128790203988437500" remote="131534932800000000" />
<file name="otam-takim-t.jpg" server="server251.web-hosting.com/public_html/" local="128790203988906250" remote="131534932800000000" />
<file name="otam-takim.jpg" server="server251.web-hosting.com/public_html/" local="128790203989375000" remote="131534932800000000" />
<file name="otam-yaris.jpg" server="server251.web-hosting.com/public_html/" local="128790203989531250" remote="131534932800000000" />
<file name="sakarya-takim-t.jpg" server="server251.web-hosting.com/public_html/" local="128790203989843750" remote="131534932800000000" />
<file name="sakarya-takim.jpg" server="server251.web-hosting.com/public_html/" local="128790203990156250" remote="131534932800000000" />
<file name="sakarya-yaris-t.jpg" server="server251.web-hosting.com/public_html/" local="128790203990312500" remote="131534932800000000" />
<file name="sakarya-yaris.jpg" server="server251.web-hosting.com/public_html/" local="128790203990781250" remote="131534932800000000" />
<file name="sdu-takim-t.jpg" server="server251.web-hosting.com/public_html/" local="128790203990937500" remote="131534932800000000" />
<file name="sdu-takim.jpg" server="server251.web-hosting.com/public_html/" local="128790203991406250" remote="131534932800000000" />
<file name="start.jpg" server="server251.web-hosting.com/public_html/" local="128790203991718750" remote="131534932800000000" />
<file name="takimlar.jpg" server="server251.web-hosting.com/public_html/" local="128790203992343750" remote="131534932800000000" />
<file name="yaris-start.jpg" server="server251.web-hosting.com/public_html/" local="128790203992812500" remote="131534932800000000" />
<file name="yaris.jpg" server="server251.web-hosting.com/public_html/" local="128790203993281250" remote="131534932800000000" />
<file name="yeditepe-takim-t.jpg" server="server251.web-hosting.com/public_html/" local="128790203993750000" remote="131534932800000000" />
<file name="yeditepe-takim.jpg" server="server251.web-hosting.com/public_html/" local="128790203994218750" remote="131534932800000000" />
<file name="yeditepe-yaris-t.jpg" server="server251.web-hosting.com/public_html/" local="128790203994531250" remote="131534932800000000" />
<file name="yeditepe-yaris.jpg" server="server251.web-hosting.com/public_html/" local="128790203994843750" remote="131534932800000000" />
<file name="ytu-takim-t.jpg" server="server251.web-hosting.com/public_html/" local="128790203995000000" remote="131534932800000000" />
<file name="ytu-takim.jpg" server="server251.web-hosting.com/public_html/" local="128790203995468750" remote="131534932800000000" />
<file name="ytu-yaris-t.jpg" server="server251.web-hosting.com/public_html/" local="128790203995781250" remote="131534932800000000" />
<file name="ytu-yaris.jpg" server="server251.web-hosting.com/public_html/" local="128790203996250000" remote="131534932800000000" />
</dwsync>